{"title": "", "melodies": [{"lyrics": [{"time": 1.0, "lyric": "\u65e5"}, {"time": 1.5, "lyric": "\u6708"}, {"time": 4.0, "lyric": "\u8f6e"}, {"time": 5.0, "lyric": "\u6d41"}, {"time": 8.0, "lyric": "\u50ac"}, {"time": 9.0, "lyric": "\u6653"}, {"time": 9.5, "lyric": "\uff08\u54c7\uff09"}, {"time": 10.0, "lyric": "\u7bad\uff0c"}], "melody": [{"time": 1.0, "pitch": 61}, {"time": 1.0625, "pitch": 61}, {"time": 1.125, "pitch": 61}, {"time": 1.1875, "pitch": 61}, {"time": 1.25, "pitch": 66}, {"time": 1.3125, "pitch": 66}, {"time": 1.375, "pitch": 66}, {"time": 1.4375, "pitch": 66}, {"time": 1.5, "pitch": 64}, {"time": 1.5625, "pitch": 64}, {"time": 1.625, "pitch": 64}, {"time": 1.6875, "pitch": 64}, {"time": 1.75, "pitch": 64}, {"time": 1.8125, "pitch": 64}, {"time": 1.875, "pitch": 64}, {"time": 1.9375, "pitch": 64}, {"time": 2.0, "pitch": 64}, {"time": 2.0625, "pitch": 64}, {"time": 2.125, "pitch": 64}, {"time": 2.1875, "pitch": 64}, {"time": 2.25, "pitch": 66}, {"time": 2.3125, "pitch": 66}, {"time": 2.375, "pitch": 66}, {"time": 2.4375, "pitch": 66}, {"time": 2.5, "pitch": 68}, {"time": 2.5625, "pitch": 68}, {"time": 2.625, "pitch": 68}, {"time": 2.6875, "pitch": 68}, {"time": 2.75, "pitch": 68}, {"time": 2.8125, "pitch": 68}, {"time": 2.875, "pitch": 68}, {"time": 2.9375, "pitch": 68}, {"time": 3.0, "pitch": 0}, {"time": 3.0625, "pitch": 0}, {"time": 3.125, "pitch": 0}, {"time": 3.1875, "pitch": 0}, {"time": 3.25, "pitch": 0}, {"time": 3.3125, "pitch": 0}, {"time": 3.375, "pitch": 0}, {"time": 3.4375, "pitch": 0}, {"time": 3.5, "pitch": 0}, {"time": 3.5625, "pitch": 0}, {"time": 3.625, "pitch": 0}, {"time": 3.6875, "pitch": 0}, {"time": 3.75, "pitch": 0}, {"time": 3.8125, "pitch": 0}, {"time": 3.875, "pitch": 0}, {"time": 3.9375, "pitch": 0}, {"time": 4.0, "pitch": 66}, {"time": 4.0625, "pitch": 66}, {"time": 4.125, "pitch": 66}, {"time": 4.1875, "pitch": 66}, {"time": 4.25, "pitch": 71}, {"time": 4.3125, "pitch": 71}, {"time": 4.375, "pitch": 71}, {"time": 4.4375, "pitch": 71}, {"time": 4.5, "pitch": 68}, {"time": 4.5625, "pitch": 68}, {"time": 4.625, "pitch": 68}, {"time": 4.6875, "pitch": 68}, {"time": 4.75, "pitch": 66}, {"time": 4.8125, "pitch": 66}, {"time": 4.875, "pitch": 66}, {"time": 4.9375, "pitch": 66}, {"time": 5.0, "pitch": 64}, {"time": 5.0625, "pitch": 64}, {"time": 5.125, "pitch": 64}, {"time": 5.1875, "pitch": 64}, {"time": 5.25, "pitch": 64}, {"time": 5.3125, "pitch": 64}, {"time": 5.375, "pitch": 64}, {"time": 5.4375, "pitch": 64}, {"time": 5.5, "pitch": 66}, {"time": 5.5625, "pitch": 66}, {"time": 5.625, "pitch": 66}, {"time": 5.6875, "pitch": 66}, {"time": 5.75, "pitch": 66}, {"time": 5.8125, "pitch": 66}, {"time": 5.875, "pitch": 66}, {"time": 5.9375, "pitch": 66}, {"time": 6.0, "pitch": 0}, {"time": 6.0625, "pitch": 0}, {"time": 6.125, "pitch": 0}, {"time": 6.1875, "pitch": 0}, {"time": 6.25, "pitch": 0}, {"time": 6.3125, "pitch": 0}, {"time": 6.375, "pitch": 0}, {"time": 6.4375, "pitch": 0}, {"time": 6.5, "pitch": 0}, {"time": 6.5625, "pitch": 0}, {"time": 6.625, "pitch": 0}, {"time": 6.6875, "pitch": 0}, {"time": 6.75, "pitch": 0}, {"time": 6.8125, "pitch": 0}, {"time": 6.875, "pitch": 0}, {"time": 6.9375, "pitch": 0}, {"time": 7.0, "pitch": 0}, {"time": 7.0625, "pitch": 0}, {"time": 7.125, "pitch": 0}, {"time": 7.1875, "pitch": 0}, {"time": 7.25, "pitch": 0}, {"time": 7.3125, "pitch": 0}, {"time": 7.375, "pitch": 0}, {"time": 7.4375, "pitch": 0}, {"time": 7.5, "pitch": 0}, {"time": 7.5625, "pitch": 0}, {"time": 7.625, "pitch": 0}, {"time": 7.6875, "pitch": 0}, {"time": 7.75, "pitch": 0}, {"time": 7.8125, "pitch": 0}, {"time": 7.875, "pitch": 0}, {"time": 7.9375, "pitch": 0}, {"time": 8.0, "pitch": 66}, {"time": 8.0625, "pitch": 66}, {"time": 8.125, "pitch": 66}, {"time": 8.1875, "pitch": 66}, {"time": 8.25, "pitch": 66}, {"time": 8.3125, "pitch": 66}, {"time": 8.375, "pitch": 66}, {"time": 8.4375, "pitch": 66}, {"time": 8.5, "pitch": 66}, {"time": 8.5625, "pitch": 66}, {"time": 8.625, "pitch": 66}, {"time": 8.6875, "pitch": 66}, {"time": 8.75, "pitch": 66}, {"time": 8.8125, "pitch": 66}, {"time": 8.875, "pitch": 66}, {"time": 8.9375, "pitch": 66}, {"time": 9.0, "pitch": 64}, {"time": 9.0625, "pitch": 64}, {"time": 9.125, "pitch": 64}, {"time": 9.1875, "pitch": 64}, {"time": 9.25, "pitch": 64}, {"time": 9.3125, "pitch": 64}, {"time": 9.375, "pitch": 64}, {"time": 9.4375, "pitch": 64}, {"time": 9.5, "pitch": 68}, {"time": 9.5625, "pitch": 68}, {"time": 9.625, "pitch": 68}, {"time": 9.6875, "pitch": 68}, {"time": 9.75, "pitch": 68}, {"time": 9.8125, "pitch": 68}, {"time": 9.875, "pitch": 68}, {"time": 9.9375, "pitch": 68}, {"time": 10.0, "pitch": 66}, {"time": 10.0625, "pitch": 66}, {"time": 10.125, "pitch": 66}, {"time": 10.1875, "pitch": 66}, {"time": 10.25, "pitch": 66}, {"time": 10.3125, "pitch": 66}, {"time": 10.375, "pitch": 66}, {"time": 10.4375, "pitch": 66}, {"time": 10.5, "pitch": 66}, {"time": 10.5625, "pitch": 66}, {"time": 10.625, "pitch": 66}, {"time": 10.6875, "pitch": 66}, {"time": 10.75, "pitch": 66}, {"time": 10.8125, "pitch": 66}, {"time": 10.875, "pitch": 66}, {"time": 10.9375, "pitch": 66}, {"time": 11.0, "pitch": 66}, {"time": 11.0625, "pitch": 66}, {"time": 11.125, "pitch": 66}, {"time": 11.1875, "pitch": 66}, {"time": 11.25, "pitch": 66}, {"time": 11.3125, "pitch": 66}, {"time": 11.375, "pitch": 66}, {"time": 11.4375, "pitch": 66}, {"time": 11.5, "pitch": 66}, {"time": 11.5625, "pitch": 66}, {"time": 11.625, "pitch": 66}, {"time": 11.6875, "pitch": 66}, {"time": 11.75, "pitch": 66}, {"time": 11.8125, "pitch": 66}, {"time": 11.875, "pitch": 66}, {"time": 11.9375, "pitch": 66}], "id": ["lsxp-YiShiWu-YuCangJian", "0"]}, {"lyrics": [{"time": 1.0, "lyric": "\u6068"}, {"time": 1.5, "lyric": "\u5e73"}, {"time": 2.5, "lyric": "\u738b"}, {"time": 4.0, "lyric": "\u65e0"}, {"time": 5.0, "lyric": "\u9053"}, {"time": 8.0, "lyric": "\u7eb2"}, {"time": 9.0, "lyric": "\u5e38"}, {"time": 10.0, "lyric": "\u4e71\uff0c"}], "melody": [{"time": 1.0, "pitch": 64}, {"time": 1.0625, "pitch": 64}, {"time": 1.125, "pitch": 64}, {"time": 1.1875, "pitch": 64}, {"time": 1.25, "pitch": 66}, {"time": 1.3125, "pitch": 66}, {"time": 1.375, "pitch": 66}, {"time": 1.4375, "pitch": 66}, {"time": 1.5, "pitch": 64}, {"time": 1.5625, "pitch": 64}, {"time": 1.625, "pitch": 64}, {"time": 1.6875, "pitch": 64}, {"time": 1.75, "pitch": 66}, {"time": 1.8125, "pitch": 66}, {"time": 1.875, "pitch": 66}, {"time": 1.9375, "pitch": 66}, {"time": 2.0, "pitch": 66}, {"time": 2.0625, "pitch": 66}, {"time": 2.125, "pitch": 66}, {"time": 2.1875, "pitch": 66}, {"time": 2.25, "pitch": 66}, {"time": 2.3125, "pitch": 66}, {"time": 2.375, "pitch": 66}, {"time": 2.4375, "pitch": 66}, {"time": 2.5, "pitch": 66}, {"time": 2.5625, "pitch": 66}, {"time": 2.625, "pitch": 66}, {"time": 2.6875, "pitch": 66}, {"time": 2.75, "pitch": 64}, {"time": 2.8125, "pitch": 64}, {"time": 2.875, "pitch": 64}, {"time": 2.9375, "pitch": 64}, {"time": 3.0, "pitch": 68}, {"time": 3.0625, "pitch": 68}, {"time": 3.125, "pitch": 68}, {"time": 3.1875, "pitch": 68}, {"time": 3.25, "pitch": 68}, {"time": 3.3125, "pitch": 68}, {"time": 3.375, "pitch": 68}, {"time": 3.4375, "pitch": 68}, {"time": 3.5, "pitch": 0}, {"time": 3.5625, "pitch": 0}, {"time": 3.625, "pitch": 0}, {"time": 3.6875, "pitch": 0}, {"time": 3.75, "pitch": 0}, {"time": 3.8125, "pitch": 0}, {"time": 3.875, "pitch": 0}, {"time": 3.9375, "pitch": 0}, {"time": 4.0, "pitch": 66}, {"time": 4.0625, "pitch": 66}, {"time": 4.125, "pitch": 66}, {"time": 4.1875, "pitch": 66}, {"time": 4.25, "pitch": 71}, {"time": 4.3125, "pitch": 71}, {"time": 4.375, "pitch": 71}, {"time": 4.4375, "pitch": 71}, {"time": 4.5, "pitch": 68}, {"time": 4.5625, "pitch": 68}, {"time": 4.625, "pitch": 68}, {"time": 4.6875, "pitch": 68}, {"time": 4.75, "pitch": 64}, {"time": 4.8125, "pitch": 64}, {"time": 4.875, "pitch": 64}, {"time": 4.9375, "pitch": 64}, {"time": 5.0, "pitch": 66}, {"time": 5.0625, "pitch": 66}, {"time": 5.125, "pitch": 66}, {"time": 5.1875, "pitch": 66}, {"time": 5.25, "pitch": 66}, {"time": 5.3125, "pitch": 66}, {"time": 5.375, "pitch": 66}, {"time": 5.4375, "pitch": 66}, {"time": 5.5, "pitch": 64}, {"time": 5.5625, "pitch": 64}, {"time": 5.625, "pitch": 64}, {"time": 5.6875, "pitch": 64}, {"time": 5.75, "pitch": 64}, {"time": 5.8125, "pitch": 64}, {"time": 5.875, "pitch": 64}, {"time": 5.9375, "pitch": 64}, {"time": 6.0, "pitch": 0}, {"time": 6.0625, "pitch": 0}, {"time": 6.125, "pitch": 0}, {"time": 6.1875, "pitch": 0}, {"time": 6.25, "pitch": 0}, {"time": 6.3125, "pitch": 0}, {"time": 6.375, "pitch": 0}, {"time": 6.4375, "pitch": 0}, {"time": 6.5, "pitch": 0}, {"time": 6.5625, "pitch": 0}, {"time": 6.625, "pitch": 0}, {"time": 6.6875, "pitch": 0}, {"time": 6.75, "pitch": 0}, {"time": 6.8125, "pitch": 0}, {"time": 6.875, "pitch": 0}, {"time": 6.9375, "pitch": 0}, {"time": 7.0, "pitch": 0}, {"time": 7.0625, "pitch": 0}, {"time": 7.125, "pitch": 0}, {"time": 7.1875, "pitch": 0}, {"time": 7.25, "pitch": 0}, {"time": 7.3125, "pitch": 0}, {"time": 7.375, "pitch": 0}, {"time": 7.4375, "pitch": 0}, {"time": 7.5, "pitch": 0}, {"time": 7.5625, "pitch": 0}, {"time": 7.625, "pitch": 0}, {"time": 7.6875, "pitch": 0}, {"time": 7.75, "pitch": 0}, {"time": 7.8125, "pitch": 0}, {"time": 7.875, "pitch": 0}, {"time": 7.9375, "pitch": 0}, {"time": 8.0, "pitch": 66}, {"time": 8.0625, "pitch": 66}, {"time": 8.125, "pitch": 66}, {"time": 8.1875, "pitch": 66}, {"time": 8.25, "pitch": 66}, {"time": 8.3125, "pitch": 66}, {"time": 8.375, "pitch": 66}, {"time": 8.4375, "pitch": 66}, {"time": 8.5, "pitch": 66}, {"time": 8.5625, "pitch": 66}, {"time": 8.625, "pitch": 66}, {"time": 8.6875, "pitch": 66}, {"time": 8.75, "pitch": 66}, {"time": 8.8125, "pitch": 66}, {"time": 8.875, "pitch": 66}, {"time": 8.9375, "pitch": 66}, {"time": 9.0, "pitch": 66}, {"time": 9.0625, "pitch": 66}, {"time": 9.125, "pitch": 66}, {"time": 9.1875, "pitch": 66}, {"time": 9.25, "pitch": 66}, {"time": 9.3125, "pitch": 66}, {"time": 9.375, "pitch": 66}, {"time": 9.4375, "pitch": 66}, {"time": 9.5, "pitch": 61}, {"time": 9.5625, "pitch": 61}, {"time": 9.625, "pitch": 61}, {"time": 9.6875, "pitch": 61}, {"time": 9.75, "pitch": 64}, {"time": 9.8125, "pitch": 64}, {"time": 9.875, "pitch": 64}, {"time": 9.9375, "pitch": 64}, {"time": 10.0, "pitch": 66}, {"time": 10.0625, "pitch": 66}, {"time": 10.125, "pitch": 66}, {"time": 10.1875, "pitch": 66}, {"time": 10.25, "pitch": 66}, {"time": 10.3125, "pitch": 66}, {"time": 10.375, "pitch": 66}, {"time": 10.4375, "pitch": 66}, {"time": 10.5, "pitch": 66}, {"time": 10.5625, "pitch": 66}, {"time": 10.625, "pitch": 66}, {"time": 10.6875, "pitch": 66}, {"time": 10.75, "pitch": 66}, {"time": 10.8125, "pitch": 66}, {"time": 10.875, "pitch": 66}, {"time": 10.9375, "pitch": 66}, {"time": 11.0, "pitch": 66}, {"time": 11.0625, "pitch": 66}, {"time": 11.125, "pitch": 66}, {"time": 11.1875, "pitch": 66}, {"time": 11.25, "pitch": 66}, {"time": 11.3125, "pitch": 66}, {"time": 11.375, "pitch": 66}, {"time": 11.4375, "pitch": 66}], "id": ["lsxp-YiShiWu-YuCangJian", "1"]}, {"lyrics": [{"time": 1.0, "lyric": "\u5b9e"}, {"time": 1.5, "lyric": "\u6307"}, {"time": 1.75, "lyric": "\uff08\u558f\uff09"}, {"time": 2.5, "lyric": "\u671b"}, {"time": 4.0, "lyric": "\u5230"}, {"time": 4.5, "lyric": "\u5434"}, {"time": 5.0, "lyric": "\u56fd"}, {"time": 8.0, "lyric": "\u501f"}, {"time": 9.0, "lyric": "\u5175"}, {"time": 10.5, "lyric": "\uff08\u5450\uff09"}, {"time": 12.0, "lyric": "\u8f6c\uff0c"}], "melody": [{"time": 1.0, "pitch": 64}, {"time": 1.0625, "pitch": 64}, {"time": 1.125, "pitch": 64}, {"time": 1.1875, "pitch": 64}, {"time": 1.25, "pitch": 66}, {"time": 1.3125, "pitch": 66}, {"time": 1.375, "pitch": 66}, {"time": 1.4375, "pitch": 66}, {"time": 1.5, "pitch": 64}, {"time": 1.5625, "pitch": 64}, {"time": 1.625, "pitch": 64}, {"time": 1.6875, "pitch": 64}, {"time": 1.75, "pitch": 66}, {"time": 1.8125, "pitch": 66}, {"time": 1.875, "pitch": 66}, {"time": 1.9375, "pitch": 66}, {"time": 2.0, "pitch": 66}, {"time": 2.0625, "pitch": 66}, {"time": 2.125, "pitch": 66}, {"time": 2.1875, "pitch": 66}, {"time": 2.25, "pitch": 66}, {"time": 2.3125, "pitch": 66}, {"time": 2.375, "pitch": 66}, {"time": 2.4375, "pitch": 66}, {"time": 2.5, "pitch": 68}, {"time": 2.5625, "pitch": 68}, {"time": 2.625, "pitch": 68}, {"time": 2.6875, "pitch": 68}, {"time": 2.75, "pitch": 66}, {"time": 2.8125, "pitch": 66}, {"time": 2.875, "pitch": 66}, {"time": 2.9375, "pitch": 66}, {"time": 3.0, "pitch": 68}, {"time": 3.0625, "pitch": 68}, {"time": 3.125, "pitch": 68}, {"time": 3.1875, "pitch": 68}, {"time": 3.25, "pitch": 68}, {"time": 3.3125, "pitch": 68}, {"time": 3.375, "pitch": 68}, {"time": 3.4375, "pitch": 68}, {"time": 3.5, "pitch": 0}, {"time": 3.5625, "pitch": 0}, {"time": 3.625, "pitch": 0}, {"time": 3.6875, "pitch": 0}, {"time": 3.75, "pitch": 0}, {"time": 3.8125, "pitch": 0}, {"time": 3.875, "pitch": 0}, {"time": 3.9375, "pitch": 0}, {"time": 4.0, "pitch": 66}, {"time": 4.0625, "pitch": 66}, {"time": 4.125, "pitch": 66}, {"time": 4.1875, "pitch": 66}, {"time": 4.25, "pitch": 71}, {"time": 4.3125, "pitch": 71}, {"time": 4.375, "pitch": 71}, {"time": 4.4375, "pitch": 71}, {"time": 4.5, "pitch": 68}, {"time": 4.5625, "pitch": 68}, {"time": 4.625, "pitch": 68}, {"time": 4.6875, "pitch": 68}, {"time": 4.75, "pitch": 66}, {"time": 4.8125, "pitch": 66}, {"time": 4.875, "pitch": 66}, {"time": 4.9375, "pitch": 66}, {"time": 5.0, "pitch": 64}, {"time": 5.0625, "pitch": 64}, {"time": 5.125, "pitch": 64}, {"time": 5.1875, "pitch": 64}, {"time": 5.25, "pitch": 64}, {"time": 5.3125, "pitch": 64}, {"time": 5.375, "pitch": 64}, {"time": 5.4375, "pitch": 64}, {"time": 5.5, "pitch": 66}, {"time": 5.5625, "pitch": 66}, {"time": 5.625, "pitch": 66}, {"time": 5.6875, "pitch": 66}, {"time": 5.75, "pitch": 66}, {"time": 5.8125, "pitch": 66}, {"time": 5.875, "pitch": 66}, {"time": 5.9375, "pitch": 66}, {"time": 6.0, "pitch": 0}, {"time": 6.0625, "pitch": 0}, {"time": 6.125, "pitch": 0}, {"time": 6.1875, "pitch": 0}, {"time": 6.25, "pitch": 0}, {"time": 6.3125, "pitch": 0}, {"time": 6.375, "pitch": 0}, {"time": 6.4375, "pitch": 0}, {"time": 6.5, "pitch": 0}, {"time": 6.5625, "pitch": 0}, {"time": 6.625, "pitch": 0}, {"time": 6.6875, "pitch": 0}, {"time": 6.75, "pitch": 0}, {"time": 6.8125, "pitch": 0}, {"time": 6.875, "pitch": 0}, {"time": 6.9375, "pitch": 0}, {"time": 7.0, "pitch": 0}, {"time": 7.0625, "pitch": 0}, {"time": 7.125, "pitch": 0}, {"time": 7.1875, "pitch": 0}, {"time": 7.25, "pitch": 0}, {"time": 7.3125, "pitch": 0}, {"time": 7.375, "pitch": 0}, {"time": 7.4375, "pitch": 0}, {"time": 7.5, "pitch": 0}, {"time": 7.5625, "pitch": 0}, {"time": 7.625, "pitch": 0}, {"time": 7.6875, "pitch": 0}, {"time": 7.75, "pitch": 0}, {"time": 7.8125, "pitch": 0}, {"time": 7.875, "pitch": 0}, {"time": 7.9375, "pitch": 0}, {"time": 8.0, "pitch": 61}, {"time": 8.0625, "pitch": 61}, {"time": 8.125, "pitch": 61}, {"time": 8.1875, "pitch": 61}, {"time": 8.25, "pitch": 61}, {"time": 8.3125, "pitch": 61}, {"time": 8.375, "pitch": 61}, {"time": 8.4375, "pitch": 61}, {"time": 8.5, "pitch": 64}, {"time": 8.5625, "pitch": 64}, {"time": 8.625, "pitch": 64}, {"time": 8.6875, "pitch": 64}, {"time": 8.75, "pitch": 64}, {"time": 8.8125, "pitch": 64}, {"time": 8.875, "pitch": 64}, {"time": 8.9375, "pitch": 64}, {"time": 9.0, "pitch": 68}, {"time": 9.0625, "pitch": 68}, {"time": 9.125, "pitch": 68}, {"time": 9.1875, "pitch": 68}, {"time": 9.25, "pitch": 68}, {"time": 9.3125, "pitch": 68}, {"time": 9.375, "pitch": 68}, {"time": 9.4375, "pitch": 68}, {"time": 9.5, "pitch": 68}, {"time": 9.5625, "pitch": 68}, {"time": 9.625, "pitch": 68}, {"time": 9.6875, "pitch": 68}, {"time": 9.75, "pitch": 68}, {"time": 9.8125, "pitch": 68}, {"time": 9.875, "pitch": 68}, {"time": 9.9375, "pitch": 68}, {"time": 10.0, "pitch": 68}, {"time": 10.0625, "pitch": 68}, {"time": 10.125, "pitch": 68}, {"time": 10.1875, "pitch": 68}, {"time": 10.25, "pitch": 68}, {"time": 10.3125, "pitch": 68}, {"time": 10.375, "pitch": 68}, {"time": 10.4375, "pitch": 68}, {"time": 10.5, "pitch": 68}, {"time": 10.5625, "pitch": 68}, {"time": 10.625, "pitch": 68}, {"time": 10.6875, "pitch": 68}, {"time": 10.75, "pitch": 68}, {"time": 10.8125, "pitch": 68}, {"time": 10.875, "pitch": 68}, {"time": 10.9375, "pitch": 68}, {"time": 11.0, "pitch": 66}, {"time": 11.0625, "pitch": 66}, {"time": 11.125, "pitch": 66}, {"time": 11.1875, "pitch": 66}, {"time": 11.25, "pitch": 66}, {"time": 11.3125, "pitch": 66}, {"time": 11.375, "pitch": 66}, {"time": 11.4375, "pitch": 66}, {"time": 11.5, "pitch": 64}, {"time": 11.5625, "pitch": 64}, {"time": 11.625, "pitch": 64}, {"time": 11.6875, "pitch": 64}, {"time": 11.75, "pitch": 64}, {"time": 11.8125, "pitch": 64}, {"time": 11.875, "pitch": 64}, {"time": 11.9375, "pitch": 64}, {"time": 12.0, "pitch": 64}, {"time": 12.0625, "pitch": 64}, {"time": 12.125, "pitch": 64}, {"time": 12.1875, "pitch": 64}, {"time": 12.25, "pitch": 61}, {"time": 12.3125, "pitch": 61}, {"time": 12.375, "pitch": 61}, {"time": 12.4375, "pitch": 61}, {"time": 12.5, "pitch": 66}, {"time": 12.5625, "pitch": 66}, {"time": 12.625, "pitch": 66}, {"time": 12.6875, "pitch": 66}, {"time": 12.75, "pitch": 66}, {"time": 12.8125, "pitch": 66}, {"time": 12.875, "pitch": 66}, {"time": 12.9375, "pitch": 66}], "id": ["lsxp-YiShiWu-YuCangJian", "2"]}, {"lyrics": [{"time": 1.0, "lyric": "\u6df1"}, {"time": 1.5, "lyric": "\u5bab"}, {"time": 4.0, "lyric": "\u65e0"}, {"time": 4.5, "lyric": "\uff08\u54c7\uff09"}, {"time": 5.0, "lyric": "\u5904"}, {"time": 8.0, "lyric": "\u4e0d"}, {"time": 11.0, "lyric": "\u98de"}, {"time": 12.0, "lyric": "\u82b1\uff0c"}], "melody": [{"time": 1.0, "pitch": 71}, {"time": 1.0625, "pitch": 71}, {"time": 1.125, "pitch": 71}, {"time": 1.1875, "pitch": 71}, {"time": 1.25, "pitch": 71}, {"time": 1.3125, "pitch": 71}, {"time": 1.375, "pitch": 71}, {"time": 1.4375, "pitch": 71}, {"time": 1.5, "pitch": 71}, {"time": 1.5625, "pitch": 71}, {"time": 1.625, "pitch": 71}, {"time": 1.6875, "pitch": 71}, {"time": 1.75, "pitch": 73}, {"time": 1.8125, "pitch": 73}, {"time": 1.875, "pitch": 73}, {"time": 1.9375, "pitch": 73}, {"time": 2.0, "pitch": 71}, {"time": 2.0625, "pitch": 71}, {"time": 2.125, "pitch": 71}, {"time": 2.1875, "pitch": 71}, {"time": 2.25, "pitch": 71}, {"time": 2.3125, "pitch": 71}, {"time": 2.375, "pitch": 71}, {"time": 2.4375, "pitch": 71}, {"time": 2.5, "pitch": 69}, {"time": 2.5625, "pitch": 69}, {"time": 2.625, "pitch": 69}, {"time": 2.6875, "pitch": 69}, {"time": 2.75, "pitch": 69}, {"time": 2.8125, "pitch": 69}, {"time": 2.875, "pitch": 69}, {"time": 2.9375, "pitch": 69}, {"time": 3.0, "pitch": 68}, {"time": 3.0625, "pitch": 68}, {"time": 3.125, "pitch": 68}, {"time": 3.1875, "pitch": 68}, {"time": 3.25, "pitch": 68}, {"time": 3.3125, "pitch": 68}, {"time": 3.375, "pitch": 68}, {"time": 3.4375, "pitch": 68}, {"time": 3.5, "pitch": 0}, {"time": 3.5625, "pitch": 0}, {"time": 3.625, "pitch": 0}, {"time": 3.6875, "pitch": 0}, {"time": 3.75, "pitch": 0}, {"time": 3.8125, "pitch": 0}, {"time": 3.875, "pitch": 0}, {"time": 3.9375, "pitch": 0}, {"time": 4.0, "pitch": 66}, {"time": 4.0625, "pitch": 66}, {"time": 4.125, "pitch": 66}, {"time": 4.1875, "pitch": 66}, {"time": 4.25, "pitch": 71}, {"time": 4.3125, "pitch": 71}, {"time": 4.375, "pitch": 71}, {"time": 4.4375, "pitch": 71}, {"time": 4.5, "pitch": 68}, {"time": 4.5625, "pitch": 68}, {"time": 4.625, "pitch": 68}, {"time": 4.6875, "pitch": 68}, {"time": 4.75, "pitch": 71}, {"time": 4.8125, "pitch": 71}, {"time": 4.875, "pitch": 71}, {"time": 4.9375, "pitch": 71}, {"time": 5.0, "pitch": 64}, {"time": 5.0625, "pitch": 64}, {"time": 5.125, "pitch": 64}, {"time": 5.1875, "pitch": 64}, {"time": 5.25, "pitch": 64}, {"time": 5.3125, "pitch": 64}, {"time": 5.375, "pitch": 64}, {"time": 5.4375, "pitch": 64}, {"time": 5.5, "pitch": 66}, {"time": 5.5625, "pitch": 66}, {"time": 5.625, "pitch": 66}, {"time": 5.6875, "pitch": 66}, {"time": 5.75, "pitch": 66}, {"time": 5.8125, "pitch": 66}, {"time": 5.875, "pitch": 66}, {"time": 5.9375, "pitch": 66}, {"time": 6.0, "pitch": 0}, {"time": 6.0625, "pitch": 0}, {"time": 6.125, "pitch": 0}, {"time": 6.1875, "pitch": 0}, {"time": 6.25, "pitch": 0}, {"time": 6.3125, "pitch": 0}, {"time": 6.375, "pitch": 0}, {"time": 6.4375, "pitch": 0}, {"time": 6.5, "pitch": 0}, {"time": 6.5625, "pitch": 0}, {"time": 6.625, "pitch": 0}, {"time": 6.6875, "pitch": 0}, {"time": 6.75, "pitch": 0}, {"time": 6.8125, "pitch": 0}, {"time": 6.875, "pitch": 0}, {"time": 6.9375, "pitch": 0}, {"time": 7.0, "pitch": 0}, {"time": 7.0625, "pitch": 0}, {"time": 7.125, "pitch": 0}, {"time": 7.1875, "pitch": 0}, {"time": 7.25, "pitch": 0}, {"time": 7.3125, "pitch": 0}, {"time": 7.375, "pitch": 0}, {"time": 7.4375, "pitch": 0}, {"time": 7.5, "pitch": 0}, {"time": 7.5625, "pitch": 0}, {"time": 7.625, "pitch": 0}, {"time": 7.6875, "pitch": 0}, {"time": 7.75, "pitch": 0}, {"time": 7.8125, "pitch": 0}, {"time": 7.875, "pitch": 0}, {"time": 7.9375, "pitch": 0}, {"time": 8.0, "pitch": 68}, {"time": 8.0625, "pitch": 68}, {"time": 8.125, "pitch": 68}, {"time": 8.1875, "pitch": 68}, {"time": 8.25, "pitch": 68}, {"time": 8.3125, "pitch": 68}, {"time": 8.375, "pitch": 68}, {"time": 8.4375, "pitch": 68}, {"time": 8.5, "pitch": 68}, {"time": 8.5625, "pitch": 68}, {"time": 8.625, "pitch": 68}, {"time": 8.6875, "pitch": 68}, {"time": 8.75, "pitch": 64}, {"time": 8.8125, "pitch": 64}, {"time": 8.875, "pitch": 64}, {"time": 8.9375, "pitch": 64}, {"time": 9.0, "pitch": 66}, {"time": 9.0625, "pitch": 66}, {"time": 9.125, "pitch": 66}, {"time": 9.1875, "pitch": 66}, {"time": 9.25, "pitch": 66}, {"time": 9.3125, "pitch": 66}, {"time": 9.375, "pitch": 66}, {"time": 9.4375, "pitch": 66}, {"time": 9.5, "pitch": 0}, {"time": 9.5625, "pitch": 0}, {"time": 9.625, "pitch": 0}, {"time": 9.6875, "pitch": 0}, {"time": 9.75, "pitch": 0}, {"time": 9.8125, "pitch": 0}, {"time": 9.875, "pitch": 0}, {"time": 9.9375, "pitch": 0}, {"time": 10.0, "pitch": 0}, {"time": 10.0625, "pitch": 0}, {"time": 10.125, "pitch": 0}, {"time": 10.1875, "pitch": 0}, {"time": 10.25, "pitch": 0}, {"time": 10.3125, "pitch": 0}, {"time": 10.375, "pitch": 0}, {"time": 10.4375, "pitch": 0}, {"time": 10.5, "pitch": 0}, {"time": 10.5625, "pitch": 0}, {"time": 10.625, "pitch": 0}, {"time": 10.6875, "pitch": 0}, {"time": 10.75, "pitch": 0}, {"time": 10.8125, "pitch": 0}, {"time": 10.875, "pitch": 0}, {"time": 10.9375, "pitch": 0}, {"time": 11.0, "pitch": 71}, {"time": 11.0625, "pitch": 71}, {"time": 11.125, "pitch": 71}, {"time": 11.1875, "pitch": 71}, {"time": 11.25, "pitch": 71}, {"time": 11.3125, "pitch": 71}, {"time": 11.375, "pitch": 71}, {"time": 11.4375, "pitch": 71}, {"time": 11.5, "pitch": 71}, {"time": 11.5625, "pitch": 71}, {"time": 11.625, "pitch": 71}, {"time": 11.6875, "pitch": 71}, {"time": 11.75, "pitch": 71}, {"time": 11.8125, "pitch": 71}, {"time": 11.875, "pitch": 71}, {"time": 11.9375, "pitch": 71}, {"time": 12.0, "pitch": 68}, {"time": 12.0625, "pitch": 68}, {"time": 12.125, "pitch": 68}, {"time": 12.1875, "pitch": 68}, {"time": 12.25, "pitch": 68}, {"time": 12.3125, "pitch": 68}, {"time": 12.375, "pitch": 68}, {"time": 12.4375, "pitch": 68}, {"time": 12.5, "pitch": 68}, {"time": 12.5625, "pitch": 68}, {"time": 12.625, "pitch": 68}, {"time": 12.6875, "pitch": 68}, {"time": 12.75, "pitch": 71}, {"time": 12.8125, "pitch": 71}, {"time": 12.875, "pitch": 71}, {"time": 12.9375, "pitch": 71}, {"time": 13.0, "pitch": 66}, {"time": 13.0625, "pitch": 66}, {"time": 13.125, "pitch": 66}, {"time": 13.1875, "pitch": 66}, {"time": 13.25, "pitch": 66}, {"time": 13.3125, "pitch": 66}, {"time": 13.375, "pitch": 66}, {"time": 13.4375, "pitch": 66}, {"time": 13.5, "pitch": 66}, {"time": 13.5625, "pitch": 66}, {"time": 13.625, "pitch": 66}, {"time": 13.6875, "pitch": 66}, {"time": 13.75, "pitch": 66}, {"time": 13.8125, "pitch": 66}, {"time": 13.875, "pitch": 66}, {"time": 13.9375, "pitch": 66}, {"time": 14.0, "pitch": 68}, {"time": 14.0625, "pitch": 68}, {"time": 14.125, "pitch": 68}, {"time": 14.1875, "pitch": 68}, {"time": 14.25, "pitch": 68}, {"time": 14.3125, "pitch": 68}, {"time": 14.375, "pitch": 68}, {"time": 14.4375, "pitch": 68}, {"time": 14.5, "pitch": 68}, {"time": 14.5625, "pitch": 68}, {"time": 14.625, "pitch": 68}, {"time": 14.6875, "pitch": 68}, {"time": 14.75, "pitch": 68}, {"time": 14.8125, "pitch": 68}, {"time": 14.875, "pitch": 68}, {"time": 14.9375, "pitch": 68}], "id": ["lsxp-ShenGongWu-LongFengChengXiang", "0"]}, {"lyrics": [{"time": 1.0, "lyric": "\u6068"}, {"time": 1.5, "lyric": "\u5e73"}, {"time": 2.5, "lyric": "\u738b"}, {"time": 4.0, "lyric": "\u65e0"}, {"time": 5.0, "lyric": "\u9053"}, {"time": 8.0, "lyric": "\u4e71"}, {"time": 9.0, "lyric": "\u695a"}, {"time": 10.0, "lyric": "\u5bab"}, {"time": 11.5, "lyric": "\uff08\u5140\uff09\uff0c"}], "melody": [{"time": 1.0, "pitch": 64}, {"time": 1.0625, "pitch": 64}, {"time": 1.125, "pitch": 64}, {"time": 1.1875, "pitch": 64}, {"time": 1.25, "pitch": 64}, {"time": 1.3125, "pitch": 64}, {"time": 1.375, "pitch": 64}, {"time": 1.4375, "pitch": 64}, {"time": 1.5, "pitch": 68}, {"time": 1.5625, "pitch": 68}, {"time": 1.625, "pitch": 68}, {"time": 1.6875, "pitch": 68}, {"time": 1.75, "pitch": 68}, {"time": 1.8125, "pitch": 68}, {"time": 1.875, "pitch": 68}, {"time": 1.9375, "pitch": 68}, {"time": 2.0, "pitch": 64}, {"time": 2.0625, "pitch": 64}, {"time": 2.125, "pitch": 64}, {"time": 2.1875, "pitch": 64}, {"time": 2.25, "pitch": 66}, {"time": 2.3125, "pitch": 66}, {"time": 2.375, "pitch": 66}, {"time": 2.4375, "pitch": 66}, {"time": 2.5, "pitch": 68}, {"time": 2.5625, "pitch": 68}, {"time": 2.625, "pitch": 68}, {"time": 2.6875, "pitch": 68}, {"time": 2.75, "pitch": 66}, {"time": 2.8125, "pitch": 66}, {"time": 2.875, "pitch": 66}, {"time": 2.9375, "pitch": 66}, {"time": 3.0, "pitch": 64}, {"time": 3.0625, "pitch": 64}, {"time": 3.125, "pitch": 64}, {"time": 3.1875, "pitch": 64}, {"time": 3.25, "pitch": 64}, {"time": 3.3125, "pitch": 64}, {"time": 3.375, "pitch": 64}, {"time": 3.4375, "pitch": 64}, {"time": 3.5, "pitch": 0}, {"time": 3.5625, "pitch": 0}, {"time": 3.625, "pitch": 0}, {"time": 3.6875, "pitch": 0}, {"time": 3.75, "pitch": 0}, {"time": 3.8125, "pitch": 0}, {"time": 3.875, "pitch": 0}, {"time": 3.9375, "pitch": 0}, {"time": 4.0, "pitch": 68}, {"time": 4.0625, "pitch": 68}, {"time": 4.125, "pitch": 68}, {"time": 4.1875, "pitch": 68}, {"time": 4.25, "pitch": 68}, {"time": 4.3125, "pitch": 68}, {"time": 4.375, "pitch": 71}, {"time": 4.4375, "pitch": 71}, {"time": 4.5, "pitch": 68}, {"time": 4.5625, "pitch": 68}, {"time": 4.625, "pitch": 68}, {"time": 4.6875, "pitch": 68}, {"time": 4.75, "pitch": 64}, {"time": 4.8125, "pitch": 64}, {"time": 4.875, "pitch": 64}, {"time": 4.9375, "pitch": 64}, {"time": 5.0, "pitch": 66}, {"time": 5.0625, "pitch": 66}, {"time": 5.125, "pitch": 66}, {"time": 5.1875, "pitch": 66}, {"time": 5.25, "pitch": 66}, {"time": 5.3125, "pitch": 66}, {"time": 5.375, "pitch": 66}, {"time": 5.4375, "pitch": 66}, {"time": 5.5, "pitch": 64}, {"time": 5.5625, "pitch": 64}, {"time": 5.625, "pitch": 64}, {"time": 5.6875, "pitch": 64}, {"time": 5.75, "pitch": 64}, {"time": 5.8125, "pitch": 64}, {"time": 5.875, "pitch": 64}, {"time": 5.9375, "pitch": 64}, {"time": 6.0, "pitch": 0}, {"time": 6.0625, "pitch": 0}, {"time": 6.125, "pitch": 0}, {"time": 6.1875, "pitch": 0}, {"time": 6.25, "pitch": 0}, {"time": 6.3125, "pitch": 0}, {"time": 6.375, "pitch": 0}, {"time": 6.4375, "pitch": 0}, {"time": 6.5, "pitch": 0}, {"time": 6.5625, "pitch": 0}, {"time": 6.625, "pitch": 0}, {"time": 6.6875, "pitch": 0}, {"time": 6.75, "pitch": 0}, {"time": 6.8125, "pitch": 0}, {"time": 6.875, "pitch": 0}, {"time": 6.9375, "pitch": 0}, {"time": 7.0, "pitch": 0}, {"time": 7.0625, "pitch": 0}, {"time": 7.125, "pitch": 0}, {"time": 7.1875, "pitch": 0}, {"time": 7.25, "pitch": 0}, {"time": 7.3125, "pitch": 0}, {"time": 7.375, "pitch": 0}, {"time": 7.4375, "pitch": 0}, {"time": 7.5, "pitch": 0}, {"time": 7.5625, "pitch": 0}, {"time": 7.625, "pitch": 0}, {"time": 7.6875, "pitch": 0}, {"time": 7.75, "pitch": 0}, {"time": 7.8125, "pitch": 0}, {"time": 7.875, "pitch": 0}, {"time": 7.9375, "pitch": 0}, {"time": 8.0, "pitch": 68}, {"time": 8.0625, "pitch": 68}, {"time": 8.125, "pitch": 68}, {"time": 8.1875, "pitch": 68}, {"time": 8.25, "pitch": 68}, {"time": 8.3125, "pitch": 68}, {"time": 8.375, "pitch": 68}, {"time": 8.4375, "pitch": 68}, {"time": 8.5, "pitch": 68}, {"time": 8.5625, "pitch": 68}, {"time": 8.625, "pitch": 68}, {"time": 8.6875, "pitch": 68}, {"time": 8.75, "pitch": 68}, {"time": 8.8125, "pitch": 68}, {"time": 8.875, "pitch": 68}, {"time": 8.9375, "pitch": 68}, {"time": 9.0, "pitch": 68}, {"time": 9.0625, "pitch": 68}, {"time": 9.125, "pitch": 68}, {"time": 9.1875, "pitch": 68}, {"time": 9.25, "pitch": 68}, {"time": 9.3125, "pitch": 68}, {"time": 9.375, "pitch": 68}, {"time": 9.4375, "pitch": 68}, {"time": 9.5, "pitch": 66}, {"time": 9.5625, "pitch": 66}, {"time": 9.625, "pitch": 66}, {"time": 9.6875, "pitch": 66}, {"time": 9.75, "pitch": 68}, {"time": 9.8125, "pitch": 68}, {"time": 9.875, "pitch": 68}, {"time": 9.9375, "pitch": 68}, {"time": 10.0, "pitch": 69}, {"time": 10.0625, "pitch": 69}, {"time": 10.125, "pitch": 69}, {"time": 10.1875, "pitch": 69}, {"time": 10.25, "pitch": 69}, {"time": 10.3125, "pitch": 69}, {"time": 10.375, "pitch": 69}, {"time": 10.4375, "pitch": 69}, {"time": 10.5, "pitch": 69}, {"time": 10.5625, "pitch": 69}, {"time": 10.625, "pitch": 69}, {"time": 10.6875, "pitch": 69}, {"time": 10.75, "pitch": 69}, {"time": 10.8125, "pitch": 69}, {"time": 10.875, "pitch": 69}, {"time": 10.9375, "pitch": 69}, {"time": 11.0, "pitch": 69}, {"time": 11.0625, "pitch": 69}, {"time": 11.125, "pitch": 69}, {"time": 11.1875, "pitch": 69}, {"time": 11.25, "pitch": 69}, {"time": 11.3125, "pitch": 69}, {"time": 11.375, "pitch": 69}, {"time": 11.4375, "pitch": 69}, {"time": 11.5, "pitch": 69}, {"time": 11.5625, "pitch": 69}, {"time": 11.625, "pitch": 69}, {"time": 11.6875, "pitch": 69}, {"time": 11.75, "pitch": 69}, {"time": 11.8125, "pitch": 69}, {"time": 11.875, "pitch": 69}, {"time": 11.9375, "pitch": 69}, {"time": 12.0, "pitch": 68}, {"time": 12.0625, "pitch": 68}, {"time": 12.125, "pitch": 68}, {"time": 12.1875, "pitch": 68}, {"time": 12.25, "pitch": 68}, {"time": 12.3125, "pitch": 68}, {"time": 12.375, "pitch": 68}, {"time": 12.4375, "pitch": 68}, {"time": 12.5, "pitch": 68}, {"time": 12.5625, "pitch": 68}, {"time": 12.625, "pitch": 68}, {"time": 12.6875, "pitch": 68}, {"time": 12.75, "pitch": 68}, {"time": 12.8125, "pitch": 68}, {"time": 12.875, "pitch": 68}, {"time": 12.9375, "pitch": 68}, {"time": 13.0, "pitch": 68}, {"time": 13.0625, "pitch": 68}, {"time": 13.125, "pitch": 68}, {"time": 13.1875, "pitch": 68}, {"time": 13.25, "pitch": 68}, {"time": 13.3125, "pitch": 68}, {"time": 13.375, "pitch": 68}, {"time": 13.4375, "pitch": 68}, {"time": 13.5, "pitch": 68}, {"time": 13.5625, "pitch": 68}, {"time": 13.625, "pitch": 68}, {"time": 13.6875, "pitch": 68}, {"time": 13.75, "pitch": 68}, {"time": 13.8125, "pitch": 68}, {"time": 13.875, "pitch": 68}, {"time": 13.9375, "pitch": 68}, {"time": 14.0, "pitch": 68}, {"time": 14.0625, "pitch": 68}, {"time": 14.125, "pitch": 68}, {"time": 14.1875, "pitch": 68}, {"time": 14.25, "pitch": 68}, {"time": 14.3125, "pitch": 68}, {"time": 14.375, "pitch": 68}, {"time": 14.4375, "pitch": 68}, {"time": 14.5, "pitch": 68}, {"time": 14.5625, "pitch": 68}, {"time": 14.625, "pitch": 68}, {"time": 14.6875, "pitch": 68}, {"time": 14.75, "pitch": 68}, {"time": 14.8125, "pitch": 68}, {"time": 14.875, "pitch": 68}, {"time": 14.9375, "pitch": 68}, {"time": 15.0, "pitch": 68}, {"time": 15.0625, "pitch": 68}, {"time": 15.125, "pitch": 68}, {"time": 15.1875, "pitch": 68}, {"time": 15.25, "pitch": 68}, {"time": 15.3125, "pitch": 68}, {"time": 15.375, "pitch": 68}, {"time": 15.4375, "pitch": 68}], "id": ["lsxp-HenPingWang-WenZhaoGuan", "0"]}, {"lyrics": [{"time": 1.0, "lyric": "\u4e24"}, {"time": 1.5, "lyric": "\u56fd"}, {"time": 4.0, "lyric": "\u4ea4"}, {"time": 5.0, "lyric": "\u950b"}, {"time": 8.0, "lyric": "\u9f99"}, {"time": 8.5, "lyric": "\u864e"}, {"time": 9.0, "lyric": "\u6597\uff0c"}], "melody": [{"time": 1.0, "pitch": 68}, {"time": 1.0625, "pitch": 68}, {"time": 1.125, "pitch": 68}, {"time": 1.1875, "pitch": 68}, {"time": 1.25, "pitch": 68}, {"time": 1.3125, "pitch": 68}, {"time": 1.375, "pitch": 68}, {"time": 1.4375, "pitch": 68}, {"time": 1.5, "pitch": 66}, {"time": 1.5625, "pitch": 66}, {"time": 1.625, "pitch": 66}, {"time": 1.6875, "pitch": 66}, {"time": 1.75, "pitch": 66}, {"time": 1.8125, "pitch": 66}, {"time": 1.875, "pitch": 66}, {"time": 1.9375, "pitch": 66}, {"time": 2.0, "pitch": 64}, {"time": 2.0625, "pitch": 64}, {"time": 2.125, "pitch": 64}, {"time": 2.1875, "pitch": 64}, {"time": 2.25, "pitch": 64}, {"time": 2.3125, "pitch": 64}, {"time": 2.375, "pitch": 64}, {"time": 2.4375, "pitch": 64}, {"time": 2.5, "pitch": 68}, {"time": 2.5625, "pitch": 68}, {"time": 2.625, "pitch": 68}, {"time": 2.6875, "pitch": 68}, {"time": 2.75, "pitch": 68}, {"time": 2.8125, "pitch": 68}, {"time": 2.875, "pitch": 68}, {"time": 2.9375, "pitch": 68}, {"time": 3.0, "pitch": 68}, {"time": 3.0625, "pitch": 68}, {"time": 3.125, "pitch": 68}, {"time": 3.1875, "pitch": 68}, {"time": 3.25, "pitch": 68}, {"time": 3.3125, "pitch": 68}, {"time": 3.375, "pitch": 68}, {"time": 3.4375, "pitch": 68}, {"time": 3.5, "pitch": 0}, {"time": 3.5625, "pitch": 0}, {"time": 3.625, "pitch": 0}, {"time": 3.6875, "pitch": 0}, {"time": 3.75, "pitch": 0}, {"time": 3.8125, "pitch": 0}, {"time": 3.875, "pitch": 0}, {"time": 3.9375, "pitch": 0}, {"time": 4.0, "pitch": 68}, {"time": 4.0625, "pitch": 68}, {"time": 4.125, "pitch": 68}, {"time": 4.1875, "pitch": 68}, {"time": 4.25, "pitch": 68}, {"time": 4.3125, "pitch": 68}, {"time": 4.375, "pitch": 68}, {"time": 4.4375, "pitch": 68}, {"time": 4.5, "pitch": 66}, {"time": 4.5625, "pitch": 66}, {"time": 4.625, "pitch": 66}, {"time": 4.6875, "pitch": 66}, {"time": 4.75, "pitch": 66}, {"time": 4.8125, "pitch": 66}, {"time": 4.875, "pitch": 66}, {"time": 4.9375, "pitch": 66}, {"time": 5.0, "pitch": 66}, {"time": 5.0625, "pitch": 66}, {"time": 5.125, "pitch": 66}, {"time": 5.1875, "pitch": 66}, {"time": 5.25, "pitch": 66}, {"time": 5.3125, "pitch": 66}, {"time": 5.375, "pitch": 66}, {"time": 5.4375, "pitch": 66}, {"time": 5.5, "pitch": 0}, {"time": 5.5625, "pitch": 0}, {"time": 5.625, "pitch": 0}, {"time": 5.6875, "pitch": 0}, {"time": 5.75, "pitch": 0}, {"time": 5.8125, "pitch": 0}, {"time": 5.875, "pitch": 0}, {"time": 5.9375, "pitch": 0}, {"time": 6.0, "pitch": 0}, {"time": 6.0625, "pitch": 0}, {"time": 6.125, "pitch": 0}, {"time": 6.1875, "pitch": 0}, {"time": 6.25, "pitch": 0}, {"time": 6.3125, "pitch": 0}, {"time": 6.375, "pitch": 0}, {"time": 6.4375, "pitch": 0}, {"time": 6.5, "pitch": 0}, {"time": 6.5625, "pitch": 0}, {"time": 6.625, "pitch": 0}, {"time": 6.6875, "pitch": 0}, {"time": 6.75, "pitch": 0}, {"time": 6.8125, "pitch": 0}, {"time": 6.875, "pitch": 0}, {"time": 6.9375, "pitch": 0}, {"time": 7.0, "pitch": 0}, {"time": 7.0625, "pitch": 0}, {"time": 7.125, "pitch": 0}, {"time": 7.1875, "pitch": 0}, {"time": 7.25, "pitch": 0}, {"time": 7.3125, "pitch": 0}, {"time": 7.375, "pitch": 0}, {"time": 7.4375, "pitch": 0}, {"time": 7.5, "pitch": 0}, {"time": 7.5625, "pitch": 0}, {"time": 7.625, "pitch": 0}, {"time": 7.6875, "pitch": 0}, {"time": 7.75, "pitch": 0}, {"time": 7.8125, "pitch": 0}, {"time": 7.875, "pitch": 0}, {"time": 7.9375, "pitch": 0}, {"time": 8.0, "pitch": 61}, {"time": 8.0625, "pitch": 61}, {"time": 8.125, "pitch": 61}, {"time": 8.1875, "pitch": 61}, {"time": 8.25, "pitch": 61}, {"time": 8.3125, "pitch": 61}, {"time": 8.375, "pitch": 61}, {"time": 8.4375, "pitch": 61}, {"time": 8.5, "pitch": 64}, {"time": 8.5625, "pitch": 64}, {"time": 8.625, "pitch": 64}, {"time": 8.6875, "pitch": 64}, {"time": 8.75, "pitch": 64}, {"time": 8.8125, "pitch": 64}, {"time": 8.875, "pitch": 64}, {"time": 8.9375, "pitch": 64}, {"time": 9.0, "pitch": 66}, {"time": 9.0625, "pitch": 66}, {"time": 9.125, "pitch": 66}, {"time": 9.1875, "pitch": 66}, {"time": 9.25, "pitch": 66}, {"time": 9.3125, "pitch": 66}, {"time": 9.375, "pitch": 71}, {"time": 9.4375, "pitch": 71}, {"time": 9.5, "pitch": 68}, {"time": 9.5625, "pitch": 68}, {"time": 9.625, "pitch": 68}, {"time": 9.6875, "pitch": 68}, {"time": 9.75, "pitch": 64}, {"time": 9.8125, "pitch": 64}, {"time": 9.875, "pitch": 64}, {"time": 9.9375, "pitch": 64}, {"time": 10.0, "pitch": 66}, {"time": 10.0625, "pitch": 66}, {"time": 10.125, "pitch": 66}, {"time": 10.1875, "pitch": 66}, {"time": 10.25, "pitch": 66}, {"time": 10.3125, "pitch": 66}, {"time": 10.375, "pitch": 66}, {"time": 10.4375, "pitch": 66}, {"time": 10.5, "pitch": 66}, {"time": 10.5625, "pitch": 66}, {"time": 10.625, "pitch": 66}, {"time": 10.6875, "pitch": 66}, {"time": 10.75, "pitch": 66}, {"time": 10.8125, "pitch": 66}, {"time": 10.875, "pitch": 66}, {"time": 10.9375, "pitch": 66}, {"time": 11.0, "pitch": 66}, {"time": 11.0625, "pitch": 66}, {"time": 11.125, "pitch": 66}, {"time": 11.1875, "pitch": 66}, {"time": 11.25, "pitch": 66}, {"time": 11.3125, "pitch": 66}, {"time": 11.375, "pitch": 66}, {"time": 11.4375, "pitch": 66}, {"time": 11.5, "pitch": 66}, {"time": 11.5625, "pitch": 66}, {"time": 11.625, "pitch": 66}, {"time": 11.6875, "pitch": 66}, {"time": 11.75, "pitch": 66}, {"time": 11.8125, "pitch": 66}, {"time": 11.875, "pitch": 66}, {"time": 11.9375, "pitch": 66}, {"time": 12.0, "pitch": 66}, {"time": 12.0625, "pitch": 66}, {"time": 12.125, "pitch": 66}, {"time": 12.1875, "pitch": 66}, {"time": 12.25, "pitch": 66}, {"time": 12.3125, "pitch": 66}, {"time": 12.375, "pitch": 66}, {"time": 12.4375, "pitch": 66}, {"time": 12.5, "pitch": 66}, {"time": 12.5625, "pitch": 66}, {"time": 12.625, "pitch": 66}, {"time": 12.6875, "pitch": 66}, {"time": 12.75, "pitch": 66}, {"time": 12.8125, "pitch": 66}, {"time": 12.875, "pitch": 66}, {"time": 12.9375, "pitch": 66}, {"time": 13.0, "pitch": 66}, {"time": 13.0625, "pitch": 66}, {"time": 13.125, "pitch": 66}, {"time": 13.1875, "pitch": 66}, {"time": 13.25, "pitch": 66}, {"time": 13.3125, "pitch": 66}, {"time": 13.375, "pitch": 66}, {"time": 13.4375, "pitch": 66}, {"time": 13.5, "pitch": 66}, {"time": 13.5625, "pitch": 66}, {"time": 13.625, "pitch": 66}, {"time": 13.6875, "pitch": 66}, {"time": 13.75, "pitch": 66}, {"time": 13.8125, "pitch": 66}, {"time": 13.875, "pitch": 66}, {"time": 13.9375, "pitch": 66}], "id": ["lsxp-LiangGuoJiao-ShiJieTing-2", "0"]}, {"lyrics": [{"time": 1.0, "lyric": "\u7ba1"}, {"time": 1.5, "lyric": "\u5e26"}, {"time": 4.0, "lyric": "\u4e09"}, {"time": 4.5, "lyric": "\uff08\u5450\uff09"}, {"time": 5.0, "lyric": "\u519b"}, {"time": 8.0, "lyric": "\u8981"}, {"time": 9.0, "lyric": "\u5bbd"}, {"time": 10.0, "lyric": "\u539a\uff0c"}], "melody": [{"time": 1.0, "pitch": 68}, {"time": 1.0625, "pitch": 68}, {"time": 1.125, "pitch": 68}, {"time": 1.1875, "pitch": 68}, {"time": 1.25, "pitch": 68}, {"time": 1.3125, "pitch": 68}, {"time": 1.375, "pitch": 68}, {"time": 1.4375, "pitch": 68}, {"time": 1.5, "pitch": 64}, {"time": 1.5625, "pitch": 64}, {"time": 1.625, "pitch": 64}, {"time": 1.6875, "pitch": 64}, {"time": 1.75, "pitch": 66}, {"time": 1.8125, "pitch": 66}, {"time": 1.875, "pitch": 66}, {"time": 1.9375, "pitch": 66}, {"time": 2.0, "pitch": 66}, {"time": 2.0625, "pitch": 66}, {"time": 2.125, "pitch": 66}, {"time": 2.1875, "pitch": 66}, {"time": 2.25, "pitch": 66}, {"time": 2.3125, "pitch": 66}, {"time": 2.375, "pitch": 66}, {"time": 2.4375, "pitch": 66}, {"time": 2.5, "pitch": 68}, {"time": 2.5625, "pitch": 68}, {"time": 2.625, "pitch": 68}, {"time": 2.6875, "pitch": 68}, {"time": 2.75, "pitch": 66}, {"time": 2.8125, "pitch": 66}, {"time": 2.875, "pitch": 66}, {"time": 2.9375, "pitch": 66}, {"time": 3.0, "pitch": 68}, {"time": 3.0625, "pitch": 68}, {"time": 3.125, "pitch": 68}, {"time": 3.1875, "pitch": 68}, {"time": 3.25, "pitch": 68}, {"time": 3.3125, "pitch": 68}, {"time": 3.375, "pitch": 68}, {"time": 3.4375, "pitch": 68}, {"time": 3.5, "pitch": 0}, {"time": 3.5625, "pitch": 0}, {"time": 3.625, "pitch": 0}, {"time": 3.6875, "pitch": 0}, {"time": 3.75, "pitch": 0}, {"time": 3.8125, "pitch": 0}, {"time": 3.875, "pitch": 0}, {"time": 3.9375, "pitch": 0}, {"time": 4.0, "pitch": 68}, {"time": 4.0625, "pitch": 68}, {"time": 4.125, "pitch": 68}, {"time": 4.1875, "pitch": 68}, {"time": 4.25, "pitch": 68}, {"time": 4.3125, "pitch": 68}, {"time": 4.375, "pitch": 68}, {"time": 4.4375, "pitch": 68}, {"time": 4.5, "pitch": 66}, {"time": 4.5625, "pitch": 66}, {"time": 4.625, "pitch": 66}, {"time": 4.6875, "pitch": 66}, {"time": 4.75, "pitch": 66}, {"time": 4.8125, "pitch": 66}, {"time": 4.875, "pitch": 66}, {"time": 4.9375, "pitch": 66}, {"time": 5.0, "pitch": 66}, {"time": 5.0625, "pitch": 66}, {"time": 5.125, "pitch": 66}, {"time": 5.1875, "pitch": 66}, {"time": 5.25, "pitch": 66}, {"time": 5.3125, "pitch": 66}, {"time": 5.375, "pitch": 66}, {"time": 5.4375, "pitch": 66}, {"time": 5.5, "pitch": 0}, {"time": 5.5625, "pitch": 0}, {"time": 5.625, "pitch": 0}, {"time": 5.6875, "pitch": 0}, {"time": 5.75, "pitch": 0}, {"time": 5.8125, "pitch": 0}, {"time": 5.875, "pitch": 0}, {"time": 5.9375, "pitch": 0}, {"time": 6.0, "pitch": 0}, {"time": 6.0625, "pitch": 0}, {"time": 6.125, "pitch": 0}, {"time": 6.1875, "pitch": 0}, {"time": 6.25, "pitch": 0}, {"time": 6.3125, "pitch": 0}, {"time": 6.375, "pitch": 0}, {"time": 6.4375, "pitch": 0}, {"time": 6.5, "pitch": 0}, {"time": 6.5625, "pitch": 0}, {"time": 6.625, "pitch": 0}, {"time": 6.6875, "pitch": 0}, {"time": 6.75, "pitch": 0}, {"time": 6.8125, "pitch": 0}, {"time": 6.875, "pitch": 0}, {"time": 6.9375, "pitch": 0}, {"time": 7.0, "pitch": 0}, {"time": 7.0625, "pitch": 0}, {"time": 7.125, "pitch": 0}, {"time": 7.1875, "pitch": 0}, {"time": 7.25, "pitch": 0}, {"time": 7.3125, "pitch": 0}, {"time": 7.375, "pitch": 0}, {"time": 7.4375, "pitch": 0}, {"time": 7.5, "pitch": 0}, {"time": 7.5625, "pitch": 0}, {"time": 7.625, "pitch": 0}, {"time": 7.6875, "pitch": 0}, {"time": 7.75, "pitch": 0}, {"time": 7.8125, "pitch": 0}, {"time": 7.875, "pitch": 0}, {"time": 7.9375, "pitch": 0}, {"time": 8.0, "pitch": 61}, {"time": 8.0625, "pitch": 61}, {"time": 8.125, "pitch": 61}, {"time": 8.1875, "pitch": 61}, {"time": 8.25, "pitch": 61}, {"time": 8.3125, "pitch": 61}, {"time": 8.375, "pitch": 61}, {"time": 8.4375, "pitch": 61}, {"time": 8.5, "pitch": 61}, {"time": 8.5625, "pitch": 61}, {"time": 8.625, "pitch": 61}, {"time": 8.6875, "pitch": 61}, {"time": 8.75, "pitch": 61}, {"time": 8.8125, "pitch": 61}, {"time": 8.875, "pitch": 61}, {"time": 8.9375, "pitch": 61}, {"time": 9.0, "pitch": 68}, {"time": 9.0625, "pitch": 68}, {"time": 9.125, "pitch": 68}, {"time": 9.1875, "pitch": 68}, {"time": 9.25, "pitch": 68}, {"time": 9.3125, "pitch": 68}, {"time": 9.375, "pitch": 68}, {"time": 9.4375, "pitch": 68}, {"time": 9.5, "pitch": 68}, {"time": 9.5625, "pitch": 68}, {"time": 9.625, "pitch": 68}, {"time": 9.6875, "pitch": 68}, {"time": 9.75, "pitch": 68}, {"time": 9.8125, "pitch": 68}, {"time": 9.875, "pitch": 68}, {"time": 9.9375, "pitch": 68}, {"time": 10.0, "pitch": 66}, {"time": 10.0625, "pitch": 66}, {"time": 10.125, "pitch": 66}, {"time": 10.1875, "pitch": 66}, {"time": 10.25, "pitch": 66}, {"time": 10.3125, "pitch": 66}, {"time": 10.375, "pitch": 66}, {"time": 10.4375, "pitch": 66}, {"time": 10.5, "pitch": 66}, {"time": 10.5625, "pitch": 66}, {"time": 10.625, "pitch": 66}, {"time": 10.6875, "pitch": 66}, {"time": 10.75, "pitch": 66}, {"time": 10.8125, "pitch": 66}, {"time": 10.875, "pitch": 66}, {"time": 10.9375, "pitch": 66}, {"time": 11.0, "pitch": 66}, {"time": 11.0625, "pitch": 66}, {"time": 11.125, "pitch": 66}, {"time": 11.1875, "pitch": 66}, {"time": 11.25, "pitch": 66}, {"time": 11.3125, "pitch": 66}, {"time": 11.375, "pitch": 66}, {"time": 11.4375, "pitch": 66}, {"time": 11.5, "pitch": 66}, {"time": 11.5625, "pitch": 66}, {"time": 11.625, "pitch": 66}, {"time": 11.6875, "pitch": 66}, {"time": 11.75, "pitch": 66}, {"time": 11.8125, "pitch": 66}, {"time": 11.875, "pitch": 66}, {"time": 11.9375, "pitch": 66}, {"time": 12.0, "pitch": 66}, {"time": 12.0625, "pitch": 66}, {"time": 12.125, "pitch": 66}, {"time": 12.1875, "pitch": 66}, {"time": 12.25, "pitch": 66}, {"time": 12.3125, "pitch": 66}, {"time": 12.375, "pitch": 66}, {"time": 12.4375, "pitch": 66}, {"time": 12.5, "pitch": 66}, {"time": 12.5625, "pitch": 66}, {"time": 12.625, "pitch": 66}, {"time": 12.6875, "pitch": 66}, {"time": 12.75, "pitch": 66}, {"time": 12.8125, "pitch": 66}, {"time": 12.875, "pitch": 66}, {"time": 12.9375, "pitch": 66}, {"time": 13.0, "pitch": 66}, {"time": 13.0625, "pitch": 66}, {"time": 13.125, "pitch": 66}, {"time": 13.1875, "pitch": 66}, {"time": 13.25, "pitch": 66}, {"time": 13.3125, "pitch": 66}, {"time": 13.375, "pitch": 66}, {"time": 13.4375, "pitch": 66}, {"time": 13.5, "pitch": 66}, {"time": 13.5625, "pitch": 66}, {"time": 13.625, "pitch": 66}, {"time": 13.6875, "pitch": 66}, {"time": 13.75, "pitch": 66}, {"time": 13.8125, "pitch": 66}, {"time": 13.875, "pitch": 66}, {"time": 13.9375, "pitch": 66}], "id": ["lsxp-LiangGuoJiao-ShiJieTing-2", "1"]}, {"lyrics": [{"time": 1.0, "lyric": "\u6b64"}, {"time": 1.5, "lyric": "\u4e00"}, {"time": 2.5, "lyric": "\u756a"}, {"time": 4.0, "lyric": "\u9886"}, {"time": 4.5, "lyric": "\uff08\u5443\uff09"}, {"time": 5.0, "lyric": "\u5175"}, {"time": 8.0, "lyric": "\u53bb"}, {"time": 9.0, "lyric": "\u9547"}, {"time": 10.0, "lyric": "\u5b88\uff0c"}], "melody": [{"time": 1.0, "pitch": 68}, {"time": 1.0625, "pitch": 68}, {"time": 1.125, "pitch": 68}, {"time": 1.1875, "pitch": 68}, {"time": 1.25, "pitch": 68}, {"time": 1.3125, "pitch": 68}, {"time": 1.375, "pitch": 68}, {"time": 1.4375, "pitch": 68}, {"time": 1.5, "pitch": 64}, {"time": 1.5625, "pitch": 64}, {"time": 1.625, "pitch": 64}, {"time": 1.6875, "pitch": 64}, {"time": 1.75, "pitch": 66}, {"time": 1.8125, "pitch": 66}, {"time": 1.875, "pitch": 66}, {"time": 1.9375, "pitch": 66}, {"time": 2.0, "pitch": 66}, {"time": 2.0625, "pitch": 66}, {"time": 2.125, "pitch": 66}, {"time": 2.1875, "pitch": 66}, {"time": 2.25, "pitch": 66}, {"time": 2.3125, "pitch": 66}, {"time": 2.375, "pitch": 66}, {"time": 2.4375, "pitch": 66}, {"time": 2.5, "pitch": 68}, {"time": 2.5625, "pitch": 68}, {"time": 2.625, "pitch": 68}, {"time": 2.6875, "pitch": 68}, {"time": 2.75, "pitch": 66}, {"time": 2.8125, "pitch": 66}, {"time": 2.875, "pitch": 66}, {"time": 2.9375, "pitch": 66}, {"time": 3.0, "pitch": 68}, {"time": 3.0625, "pitch": 68}, {"time": 3.125, "pitch": 68}, {"time": 3.1875, "pitch": 68}, {"time": 3.25, "pitch": 68}, {"time": 3.3125, "pitch": 68}, {"time": 3.375, "pitch": 68}, {"time": 3.4375, "pitch": 68}, {"time": 3.5, "pitch": 0}, {"time": 3.5625, "pitch": 0}, {"time": 3.625, "pitch": 0}, {"time": 3.6875, "pitch": 0}, {"time": 3.75, "pitch": 0}, {"time": 3.8125, "pitch": 0}, {"time": 3.875, "pitch": 0}, {"time": 3.9375, "pitch": 0}, {"time": 4.0, "pitch": 66}, {"time": 4.0625, "pitch": 66}, {"time": 4.125, "pitch": 66}, {"time": 4.1875, "pitch": 66}, {"time": 4.25, "pitch": 66}, {"time": 4.3125, "pitch": 66}, {"time": 4.375, "pitch": 66}, {"time": 4.4375, "pitch": 66}, {"time": 4.5, "pitch": 64}, {"time": 4.5625, "pitch": 64}, {"time": 4.625, "pitch": 64}, {"time": 4.6875, "pitch": 64}, {"time": 4.75, "pitch": 66}, {"time": 4.8125, "pitch": 66}, {"time": 4.875, "pitch": 66}, {"time": 4.9375, "pitch": 66}, {"time": 5.0, "pitch": 68}, {"time": 5.0625, "pitch": 68}, {"time": 5.125, "pitch": 68}, {"time": 5.1875, "pitch": 68}, {"time": 5.25, "pitch": 68}, {"time": 5.3125, "pitch": 68}, {"time": 5.375, "pitch": 68}, {"time": 5.4375, "pitch": 68}, {"time": 5.5, "pitch": 66}, {"time": 5.5625, "pitch": 66}, {"time": 5.625, "pitch": 64}, {"time": 5.6875, "pitch": 64}, {"time": 5.75, "pitch": 61}, {"time": 5.8125, "pitch": 61}, {"time": 5.875, "pitch": 64}, {"time": 5.9375, "pitch": 64}, {"time": 6.0, "pitch": 59}, {"time": 6.0625, "pitch": 59}, {"time": 6.125, "pitch": 59}, {"time": 6.1875, "pitch": 59}, {"time": 6.25, "pitch": 59}, {"time": 6.3125, "pitch": 59}, {"time": 6.375, "pitch": 59}, {"time": 6.4375, "pitch": 59}, {"time": 6.5, "pitch": 0}, {"time": 6.5625, "pitch": 0}, {"time": 6.625, "pitch": 0}, {"time": 6.6875, "pitch": 0}, {"time": 6.75, "pitch": 0}, {"time": 6.8125, "pitch": 0}, {"time": 6.875, "pitch": 0}, {"time": 6.9375, "pitch": 0}, {"time": 7.0, "pitch": 0}, {"time": 7.0625, "pitch": 0}, {"time": 7.125, "pitch": 0}, {"time": 7.1875, "pitch": 0}, {"time": 7.25, "pitch": 0}, {"time": 7.3125, "pitch": 0}, {"time": 7.375, "pitch": 0}, {"time": 7.4375, "pitch": 0}, {"time": 7.5, "pitch": 0}, {"time": 7.5625, "pitch": 0}, {"time": 7.625, "pitch": 0}, {"time": 7.6875, "pitch": 0}, {"time": 7.75, "pitch": 0}, {"time": 7.8125, "pitch": 0}, {"time": 7.875, "pitch": 0}, {"time": 7.9375, "pitch": 0}, {"time": 8.0, "pitch": 66}, {"time": 8.0625, "pitch": 66}, {"time": 8.125, "pitch": 66}, {"time": 8.1875, "pitch": 66}, {"time": 8.25, "pitch": 66}, {"time": 8.3125, "pitch": 66}, {"time": 8.375, "pitch": 66}, {"time": 8.4375, "pitch": 66}, {"time": 8.5, "pitch": 66}, {"time": 8.5625, "pitch": 66}, {"time": 8.625, "pitch": 66}, {"time": 8.6875, "pitch": 66}, {"time": 8.75, "pitch": 64}, {"time": 8.8125, "pitch": 64}, {"time": 8.875, "pitch": 64}, {"time": 8.9375, "pitch": 64}, {"time": 9.0, "pitch": 64}, {"time": 9.0625, "pitch": 64}, {"time": 9.125, "pitch": 64}, {"time": 9.1875, "pitch": 64}, {"time": 9.25, "pitch": 66}, {"time": 9.3125, "pitch": 66}, {"time": 9.375, "pitch": 66}, {"time": 9.4375, "pitch": 66}, {"time": 9.5, "pitch": 68}, {"time": 9.5625, "pitch": 68}, {"time": 9.625, "pitch": 68}, {"time": 9.6875, "pitch": 68}, {"time": 9.75, "pitch": 68}, {"time": 9.8125, "pitch": 68}, {"time": 9.875, "pitch": 68}, {"time": 9.9375, "pitch": 68}, {"time": 10.0, "pitch": 66}, {"time": 10.0625, "pitch": 66}, {"time": 10.125, "pitch": 66}, {"time": 10.1875, "pitch": 66}, {"time": 10.25, "pitch": 66}, {"time": 10.3125, "pitch": 66}, {"time": 10.375, "pitch": 66}, {"time": 10.4375, "pitch": 66}, {"time": 10.5, "pitch": 66}, {"time": 10.5625, "pitch": 66}, {"time": 10.625, "pitch": 66}, {"time": 10.6875, "pitch": 66}, {"time": 10.75, "pitch": 66}, {"time": 10.8125, "pitch": 66}, {"time": 10.875, "pitch": 66}, {"time": 10.9375, "pitch": 66}, {"time": 11.0, "pitch": 66}, {"time": 11.0625, "pitch": 66}, {"time": 11.125, "pitch": 66}, {"time": 11.1875, "pitch": 66}, {"time": 11.25, "pitch": 66}, {"time": 11.3125, "pitch": 66}, {"time": 11.375, "pitch": 66}, {"time": 11.4375, "pitch": 66}, {"time": 11.5, "pitch": 66}, {"time": 11.5625, "pitch": 66}, {"time": 11.625, "pitch": 66}, {"time": 11.6875, "pitch": 66}, {"time": 11.75, "pitch": 66}, {"time": 11.8125, "pitch": 66}, {"time": 11.875, "pitch": 66}, {"time": 11.9375, "pitch": 66}, {"time": 12.0, "pitch": 66}, {"time": 12.0625, "pitch": 66}, {"time": 12.125, "pitch": 66}, {"time": 12.1875, "pitch": 66}, {"time": 12.25, "pitch": 66}, {"time": 12.3125, "pitch": 66}, {"time": 12.375, "pitch": 66}, {"time": 12.4375, "pitch": 66}, {"time": 12.5, "pitch": 66}, {"time": 12.5625, "pitch": 66}, {"time": 12.625, "pitch": 66}, {"time": 12.6875, "pitch": 66}, {"time": 12.75, "pitch": 66}, {"time": 12.8125, "pitch": 66}, {"time": 12.875, "pitch": 66}, {"time": 12.9375, "pitch": 66}, {"time": 13.0, "pitch": 66}, {"time": 13.0625, "pitch": 66}, {"time": 13.125, "pitch": 66}, {"time": 13.1875, "pitch": 66}, {"time": 13.25, "pitch": 66}, {"time": 13.3125, "pitch": 66}, {"time": 13.375, "pitch": 66}, {"time": 13.4375, "pitch": 66}, {"time": 13.5, "pitch": 66}, {"time": 13.5625, "pitch": 66}, {"time": 13.625, "pitch": 66}, {"time": 13.6875, "pitch": 66}, {"time": 13.75, "pitch": 66}, {"time": 13.8125, "pitch": 66}, {"time": 13.875, "pitch": 66}, {"time": 13.9375, "pitch": 66}], "id": ["lsxp-LiangGuoJiao-ShiJieTing-2", "2"]}, {"lyrics": [{"time": 1.0, "lyric": "\u4e24"}, {"time": 1.5, "lyric": "\u56fd"}, {"time": 4.0, "lyric": "\u4ea4"}, {"time": 4.5, "lyric": "\uff08\u54c7\uff09"}, {"time": 5.0, "lyric": "\u950b"}, {"time": 8.0, "lyric": "\u9f99"}, {"time": 8.5, "lyric": "\u864e"}, {"time": 9.0, "lyric": "\u6597\uff0c"}], "melody": [{"time": 1.0, "pitch": 64}, {"time": 1.0625, "pitch": 64}, {"time": 1.125, "pitch": 64}, {"time": 1.1875, "pitch": 64}, {"time": 1.25, "pitch": 66}, {"time": 1.3125, "pitch": 66}, {"time": 1.375, "pitch": 66}, {"time": 1.4375, "pitch": 66}, {"time": 1.5, "pitch": 64}, {"time": 1.5625, "pitch": 64}, {"time": 1.625, "pitch": 64}, {"time": 1.6875, "pitch": 64}, {"time": 1.75, "pitch": 66}, {"time": 1.8125, "pitch": 66}, {"time": 1.875, "pitch": 66}, {"time": 1.9375, "pitch": 66}, {"time": 2.0, "pitch": 66}, {"time": 2.0625, "pitch": 66}, {"time": 2.125, "pitch": 66}, {"time": 2.1875, "pitch": 66}, {"time": 2.25, "pitch": 66}, {"time": 2.3125, "pitch": 66}, {"time": 2.375, "pitch": 66}, {"time": 2.4375, "pitch": 66}, {"time": 2.5, "pitch": 68}, {"time": 2.5625, "pitch": 68}, {"time": 2.625, "pitch": 68}, {"time": 2.6875, "pitch": 68}, {"time": 2.75, "pitch": 68}, {"time": 2.8125, "pitch": 68}, {"time": 2.875, "pitch": 68}, {"time": 2.9375, "pitch": 68}, {"time": 3.0, "pitch": 68}, {"time": 3.0625, "pitch": 68}, {"time": 3.125, "pitch": 68}, {"time": 3.1875, "pitch": 68}, {"time": 3.25, "pitch": 68}, {"time": 3.3125, "pitch": 68}, {"time": 3.375, "pitch": 68}, {"time": 3.4375, "pitch": 68}, {"time": 3.5, "pitch": 0}, {"time": 3.5625, "pitch": 0}, {"time": 3.625, "pitch": 0}, {"time": 3.6875, "pitch": 0}, {"time": 3.75, "pitch": 0}, {"time": 3.8125, "pitch": 0}, {"time": 3.875, "pitch": 0}, {"time": 3.9375, "pitch": 0}, {"time": 4.0, "pitch": 68}, {"time": 4.0625, "pitch": 68}, {"time": 4.125, "pitch": 68}, {"time": 4.1875, "pitch": 68}, {"time": 4.25, "pitch": 68}, {"time": 4.3125, "pitch": 68}, {"time": 4.375, "pitch": 68}, {"time": 4.4375, "pitch": 68}, {"time": 4.5, "pitch": 66}, {"time": 4.5625, "pitch": 66}, {"time": 4.625, "pitch": 66}, {"time": 4.6875, "pitch": 66}, {"time": 4.75, "pitch": 66}, {"time": 4.8125, "pitch": 66}, {"time": 4.875, "pitch": 66}, {"time": 4.9375, "pitch": 66}, {"time": 5.0, "pitch": 66}, {"time": 5.0625, "pitch": 66}, {"time": 5.125, "pitch": 66}, {"time": 5.1875, "pitch": 66}, {"time": 5.25, "pitch": 66}, {"time": 5.3125, "pitch": 66}, {"time": 5.375, "pitch": 66}, {"time": 5.4375, "pitch": 66}, {"time": 5.5, "pitch": 66}, {"time": 5.5625, "pitch": 66}, {"time": 5.625, "pitch": 66}, {"time": 5.6875, "pitch": 66}, {"time": 5.75, "pitch": 0}, {"time": 5.8125, "pitch": 0}, {"time": 5.875, "pitch": 0}, {"time": 5.9375, "pitch": 0}, {"time": 6.0, "pitch": 0}, {"time": 6.0625, "pitch": 0}, {"time": 6.125, "pitch": 0}, {"time": 6.1875, "pitch": 0}, {"time": 6.25, "pitch": 0}, {"time": 6.3125, "pitch": 0}, {"time": 6.375, "pitch": 0}, {"time": 6.4375, "pitch": 0}, {"time": 6.5, "pitch": 0}, {"time": 6.5625, "pitch": 0}, {"time": 6.625, "pitch": 0}, {"time": 6.6875, "pitch": 0}, {"time": 6.75, "pitch": 0}, {"time": 6.8125, "pitch": 0}, {"time": 6.875, "pitch": 0}, {"time": 6.9375, "pitch": 0}, {"time": 7.0, "pitch": 0}, {"time": 7.0625, "pitch": 0}, {"time": 7.125, "pitch": 0}, {"time": 7.1875, "pitch": 0}, {"time": 7.25, "pitch": 0}, {"time": 7.3125, "pitch": 0}, {"time": 7.375, "pitch": 0}, {"time": 7.4375, "pitch": 0}, {"time": 7.5, "pitch": 0}, {"time": 7.5625, "pitch": 0}, {"time": 7.625, "pitch": 0}, {"time": 7.6875, "pitch": 0}, {"time": 7.75, "pitch": 0}, {"time": 7.8125, "pitch": 0}, {"time": 7.875, "pitch": 0}, {"time": 7.9375, "pitch": 0}, {"time": 8.0, "pitch": 61}, {"time": 8.0625, "pitch": 61}, {"time": 8.125, "pitch": 61}, {"time": 8.1875, "pitch": 61}, {"time": 8.25, "pitch": 66}, {"time": 8.3125, "pitch": 66}, {"time": 8.375, "pitch": 66}, {"time": 8.4375, "pitch": 66}, {"time": 8.5, "pitch": 64}, {"time": 8.5625, "pitch": 64}, {"time": 8.625, "pitch": 64}, {"time": 8.6875, "pitch": 64}, {"time": 8.75, "pitch": 64}, {"time": 8.8125, "pitch": 64}, {"time": 8.875, "pitch": 64}, {"time": 8.9375, "pitch": 64}, {"time": 9.0, "pitch": 66}, {"time": 9.0625, "pitch": 66}, {"time": 9.125, "pitch": 66}, {"time": 9.1875, "pitch": 66}, {"time": 9.25, "pitch": 66}, {"time": 9.3125, "pitch": 66}, {"time": 9.375, "pitch": 71}, {"time": 9.4375, "pitch": 71}, {"time": 9.5, "pitch": 68}, {"time": 9.5625, "pitch": 68}, {"time": 9.625, "pitch": 68}, {"time": 9.6875, "pitch": 68}, {"time": 9.75, "pitch": 64}, {"time": 9.8125, "pitch": 64}, {"time": 9.875, "pitch": 64}, {"time": 9.9375, "pitch": 64}, {"time": 10.0, "pitch": 66}, {"time": 10.0625, "pitch": 66}, {"time": 10.125, "pitch": 66}, {"time": 10.1875, "pitch": 66}, {"time": 10.25, "pitch": 66}, {"time": 10.3125, "pitch": 66}, {"time": 10.375, "pitch": 66}, {"time": 10.4375, "pitch": 66}, {"time": 10.5, "pitch": 66}, {"time": 10.5625, "pitch": 66}, {"time": 10.625, "pitch": 66}, {"time": 10.6875, "pitch": 66}, {"time": 10.75, "pitch": 66}, {"time": 10.8125, "pitch": 66}, {"time": 10.875, "pitch": 66}, {"time": 10.9375, "pitch": 66}, {"time": 11.0, "pitch": 66}, {"time": 11.0625, "pitch": 66}, {"time": 11.125, "pitch": 66}, {"time": 11.1875, "pitch": 66}], "id": ["lsxp-LiangGuoJiao-ShiJieTing-1", "0"]}, {"lyrics": [{"time": 1.0, "lyric": "\u7ba1"}, {"time": 1.5, "lyric": "\u5f85"}, {"time": 4.0, "lyric": "\u4e09"}, {"time": 4.5, "lyric": "\uff08\u54ea\uff09"}, {"time": 5.0, "lyric": "\u519b"}, {"time": 8.0, "lyric": "\u8981"}, {"time": 9.0, "lyric": "\u5bbd"}, {"time": 10.0, "lyric": "\u539a\uff0c"}], "melody": [{"time": 1.0, "pitch": 64}, {"time": 1.0625, "pitch": 64}, {"time": 1.125, "pitch": 64}, {"time": 1.1875, "pitch": 64}, {"time": 1.25, "pitch": 66}, {"time": 1.3125, "pitch": 66}, {"time": 1.375, "pitch": 66}, {"time": 1.4375, "pitch": 66}, {"time": 1.5, "pitch": 64}, {"time": 1.5625, "pitch": 64}, {"time": 1.625, "pitch": 64}, {"time": 1.6875, "pitch": 64}, {"time": 1.75, "pitch": 66}, {"time": 1.8125, "pitch": 66}, {"time": 1.875, "pitch": 66}, {"time": 1.9375, "pitch": 66}, {"time": 2.0, "pitch": 66}, {"time": 2.0625, "pitch": 66}, {"time": 2.125, "pitch": 66}, {"time": 2.1875, "pitch": 66}, {"time": 2.25, "pitch": 66}, {"time": 2.3125, "pitch": 66}, {"time": 2.375, "pitch": 66}, {"time": 2.4375, "pitch": 66}, {"time": 2.5, "pitch": 68}, {"time": 2.5625, "pitch": 68}, {"time": 2.625, "pitch": 68}, {"time": 2.6875, "pitch": 68}, {"time": 2.75, "pitch": 68}, {"time": 2.8125, "pitch": 68}, {"time": 2.875, "pitch": 68}, {"time": 2.9375, "pitch": 68}, {"time": 3.0, "pitch": 0}, {"time": 3.0625, "pitch": 0}, {"time": 3.125, "pitch": 0}, {"time": 3.1875, "pitch": 0}, {"time": 3.25, "pitch": 0}, {"time": 3.3125, "pitch": 0}, {"time": 3.375, "pitch": 0}, {"time": 3.4375, "pitch": 0}, {"time": 3.5, "pitch": 0}, {"time": 3.5625, "pitch": 0}, {"time": 3.625, "pitch": 0}, {"time": 3.6875, "pitch": 0}, {"time": 3.75, "pitch": 0}, {"time": 3.8125, "pitch": 0}, {"time": 3.875, "pitch": 0}, {"time": 3.9375, "pitch": 0}, {"time": 4.0, "pitch": 68}, {"time": 4.0625, "pitch": 68}, {"time": 4.125, "pitch": 68}, {"time": 4.1875, "pitch": 68}, {"time": 4.25, "pitch": 68}, {"time": 4.3125, "pitch": 68}, {"time": 4.375, "pitch": 68}, {"time": 4.4375, "pitch": 68}, {"time": 4.5, "pitch": 66}, {"time": 4.5625, "pitch": 66}, {"time": 4.625, "pitch": 66}, {"time": 4.6875, "pitch": 66}, {"time": 4.75, "pitch": 66}, {"time": 4.8125, "pitch": 66}, {"time": 4.875, "pitch": 66}, {"time": 4.9375, "pitch": 66}, {"time": 5.0, "pitch": 66}, {"time": 5.0625, "pitch": 66}, {"time": 5.125, "pitch": 66}, {"time": 5.1875, "pitch": 66}, {"time": 5.25, "pitch": 66}, {"time": 5.3125, "pitch": 66}, {"time": 5.375, "pitch": 66}, {"time": 5.4375, "pitch": 66}, {"time": 5.5, "pitch": 66}, {"time": 5.5625, "pitch": 66}, {"time": 5.625, "pitch": 66}, {"time": 5.6875, "pitch": 66}, {"time": 5.75, "pitch": 0}, {"time": 5.8125, "pitch": 0}, {"time": 5.875, "pitch": 0}, {"time": 5.9375, "pitch": 0}, {"time": 6.0, "pitch": 0}, {"time": 6.0625, "pitch": 0}, {"time": 6.125, "pitch": 0}, {"time": 6.1875, "pitch": 0}, {"time": 6.25, "pitch": 0}, {"time": 6.3125, "pitch": 0}, {"time": 6.375, "pitch": 0}, {"time": 6.4375, "pitch": 0}, {"time": 6.5, "pitch": 0}, {"time": 6.5625, "pitch": 0}, {"time": 6.625, "pitch": 0}, {"time": 6.6875, "pitch": 0}, {"time": 6.75, "pitch": 0}, {"time": 6.8125, "pitch": 0}, {"time": 6.875, "pitch": 0}, {"time": 6.9375, "pitch": 0}, {"time": 7.0, "pitch": 0}, {"time": 7.0625, "pitch": 0}, {"time": 7.125, "pitch": 0}, {"time": 7.1875, "pitch": 0}, {"time": 7.25, "pitch": 0}, {"time": 7.3125, "pitch": 0}, {"time": 7.375, "pitch": 0}, {"time": 7.4375, "pitch": 0}, {"time": 7.5, "pitch": 0}, {"time": 7.5625, "pitch": 0}, {"time": 7.625, "pitch": 0}, {"time": 7.6875, "pitch": 0}, {"time": 7.75, "pitch": 0}, {"time": 7.8125, "pitch": 0}, {"time": 7.875, "pitch": 0}, {"time": 7.9375, "pitch": 0}, {"time": 8.0, "pitch": 61}, {"time": 8.0625, "pitch": 61}, {"time": 8.125, "pitch": 61}, {"time": 8.1875, "pitch": 61}, {"time": 8.25, "pitch": 61}, {"time": 8.3125, "pitch": 61}, {"time": 8.375, "pitch": 64}, {"time": 8.4375, "pitch": 64}, {"time": 8.5, "pitch": 61}, {"time": 8.5625, "pitch": 61}, {"time": 8.625, "pitch": 61}, {"time": 8.6875, "pitch": 61}, {"time": 8.75, "pitch": 64}, {"time": 8.8125, "pitch": 64}, {"time": 8.875, "pitch": 64}, {"time": 8.9375, "pitch": 64}, {"time": 9.0, "pitch": 68}, {"time": 9.0625, "pitch": 68}, {"time": 9.125, "pitch": 68}, {"time": 9.1875, "pitch": 68}, {"time": 9.25, "pitch": 68}, {"time": 9.3125, "pitch": 68}, {"time": 9.375, "pitch": 68}, {"time": 9.4375, "pitch": 68}, {"time": 9.5, "pitch": 68}, {"time": 9.5625, "pitch": 68}, {"time": 9.625, "pitch": 68}, {"time": 9.6875, "pitch": 68}, {"time": 9.75, "pitch": 68}, {"time": 9.8125, "pitch": 68}, {"time": 9.875, "pitch": 68}, {"time": 9.9375, "pitch": 68}, {"time": 10.0, "pitch": 66}, {"time": 10.0625, "pitch": 66}, {"time": 10.125, "pitch": 66}, {"time": 10.1875, "pitch": 66}, {"time": 10.25, "pitch": 66}, {"time": 10.3125, "pitch": 66}, {"time": 10.375, "pitch": 66}, {"time": 10.4375, "pitch": 66}, {"time": 10.5, "pitch": 66}, {"time": 10.5625, "pitch": 66}, {"time": 10.625, "pitch": 66}, {"time": 10.6875, "pitch": 66}, {"time": 10.75, "pitch": 66}, {"time": 10.8125, "pitch": 66}, {"time": 10.875, "pitch": 66}, {"time": 10.9375, "pitch": 66}, {"time": 11.0, "pitch": 66}, {"time": 11.0625, "pitch": 66}, {"time": 11.125, "pitch": 66}, {"time": 11.1875, "pitch": 66}], "id": ["lsxp-LiangGuoJiao-ShiJieTing-1", "1"]}, {"lyrics": [{"time": 1.0, "lyric": "\u6b64"}, {"time": 1.5, "lyric": "\u4e00"}, {"time": 2.5, "lyric": "\u756a"}, {"time": 4.0, "lyric": "\u9886"}, {"time": 5.0, "lyric": "\u5175"}, {"time": 8.0, "lyric": "\u53bb"}, {"time": 9.0, "lyric": "\u9547"}, {"time": 10.0, "lyric": "\u5b88\uff0c"}], "melody": [{"time": 1.0, "pitch": 64}, {"time": 1.0625, "pitch": 64}, {"time": 1.125, "pitch": 64}, {"time": 1.1875, "pitch": 64}, {"time": 1.25, "pitch": 66}, {"time": 1.3125, "pitch": 66}, {"time": 1.375, "pitch": 66}, {"time": 1.4375, "pitch": 66}, {"time": 1.5, "pitch": 64}, {"time": 1.5625, "pitch": 64}, {"time": 1.625, "pitch": 64}, {"time": 1.6875, "pitch": 64}, {"time": 1.75, "pitch": 66}, {"time": 1.8125, "pitch": 66}, {"time": 1.875, "pitch": 66}, {"time": 1.9375, "pitch": 66}, {"time": 2.0, "pitch": 66}, {"time": 2.0625, "pitch": 66}, {"time": 2.125, "pitch": 66}, {"time": 2.1875, "pitch": 66}, {"time": 2.25, "pitch": 64}, {"time": 2.3125, "pitch": 64}, {"time": 2.375, "pitch": 64}, {"time": 2.4375, "pitch": 64}, {"time": 2.5, "pitch": 68}, {"time": 2.5625, "pitch": 68}, {"time": 2.625, "pitch": 68}, {"time": 2.6875, "pitch": 68}, {"time": 2.75, "pitch": 66}, {"time": 2.8125, "pitch": 66}, {"time": 2.875, "pitch": 66}, {"time": 2.9375, "pitch": 66}, {"time": 3.0, "pitch": 68}, {"time": 3.0625, "pitch": 68}, {"time": 3.125, "pitch": 68}, {"time": 3.1875, "pitch": 68}, {"time": 3.25, "pitch": 68}, {"time": 3.3125, "pitch": 68}, {"time": 3.375, "pitch": 68}, {"time": 3.4375, "pitch": 68}, {"time": 3.5, "pitch": 0}, {"time": 3.5625, "pitch": 0}, {"time": 3.625, "pitch": 0}, {"time": 3.6875, "pitch": 0}, {"time": 3.75, "pitch": 0}, {"time": 3.8125, "pitch": 0}, {"time": 3.875, "pitch": 0}, {"time": 3.9375, "pitch": 0}, {"time": 4.0, "pitch": 68}, {"time": 4.0625, "pitch": 68}, {"time": 4.125, "pitch": 68}, {"time": 4.1875, "pitch": 68}, {"time": 4.25, "pitch": 68}, {"time": 4.3125, "pitch": 68}, {"time": 4.375, "pitch": 68}, {"time": 4.4375, "pitch": 68}, {"time": 4.5, "pitch": 64}, {"time": 4.5625, "pitch": 64}, {"time": 4.625, "pitch": 64}, {"time": 4.6875, "pitch": 64}, {"time": 4.75, "pitch": 64}, {"time": 4.8125, "pitch": 64}, {"time": 4.875, "pitch": 64}, {"time": 4.9375, "pitch": 64}, {"time": 5.0, "pitch": 68}, {"time": 5.0625, "pitch": 68}, {"time": 5.125, "pitch": 68}, {"time": 5.1875, "pitch": 68}, {"time": 5.25, "pitch": 68}, {"time": 5.3125, "pitch": 68}, {"time": 5.375, "pitch": 68}, {"time": 5.4375, "pitch": 68}, {"time": 5.5, "pitch": 66}, {"time": 5.5625, "pitch": 66}, {"time": 5.625, "pitch": 66}, {"time": 5.6875, "pitch": 66}, {"time": 5.75, "pitch": 64}, {"time": 5.8125, "pitch": 64}, {"time": 5.875, "pitch": 64}, {"time": 5.9375, "pitch": 64}, {"time": 6.0, "pitch": 59}, {"time": 6.0625, "pitch": 59}, {"time": 6.125, "pitch": 59}, {"time": 6.1875, "pitch": 59}, {"time": 6.25, "pitch": 59}, {"time": 6.3125, "pitch": 59}, {"time": 6.375, "pitch": 59}, {"time": 6.4375, "pitch": 59}, {"time": 6.5, "pitch": 0}, {"time": 6.5625, "pitch": 0}, {"time": 6.625, "pitch": 0}, {"time": 6.6875, "pitch": 0}, {"time": 6.75, "pitch": 0}, {"time": 6.8125, "pitch": 0}, {"time": 6.875, "pitch": 0}, {"time": 6.9375, "pitch": 0}, {"time": 7.0, "pitch": 0}, {"time": 7.0625, "pitch": 0}, {"time": 7.125, "pitch": 0}, {"time": 7.1875, "pitch": 0}, {"time": 7.25, "pitch": 0}, {"time": 7.3125, "pitch": 0}, {"time": 7.375, "pitch": 0}, {"time": 7.4375, "pitch": 0}, {"time": 7.5, "pitch": 0}, {"time": 7.5625, "pitch": 0}, {"time": 7.625, "pitch": 0}, {"time": 7.6875, "pitch": 0}, {"time": 7.75, "pitch": 0}, {"time": 7.8125, "pitch": 0}, {"time": 7.875, "pitch": 0}, {"time": 7.9375, "pitch": 0}, {"time": 8.0, "pitch": 66}, {"time": 8.0625, "pitch": 66}, {"time": 8.125, "pitch": 66}, {"time": 8.1875, "pitch": 66}, {"time": 8.25, "pitch": 66}, {"time": 8.3125, "pitch": 66}, {"time": 8.375, "pitch": 66}, {"time": 8.4375, "pitch": 66}, {"time": 8.5, "pitch": 66}, {"time": 8.5625, "pitch": 66}, {"time": 8.625, "pitch": 66}, {"time": 8.6875, "pitch": 66}, {"time": 8.75, "pitch": 64}, {"time": 8.8125, "pitch": 64}, {"time": 8.875, "pitch": 64}, {"time": 8.9375, "pitch": 64}, {"time": 9.0, "pitch": 64}, {"time": 9.0625, "pitch": 64}, {"time": 9.125, "pitch": 64}, {"time": 9.1875, "pitch": 64}, {"time": 9.25, "pitch": 64}, {"time": 9.3125, "pitch": 64}, {"time": 9.375, "pitch": 66}, {"time": 9.4375, "pitch": 66}, {"time": 9.5, "pitch": 68}, {"time": 9.5625, "pitch": 68}, {"time": 9.625, "pitch": 68}, {"time": 9.6875, "pitch": 68}, {"time": 9.75, "pitch": 71}, {"time": 9.8125, "pitch": 71}, {"time": 9.875, "pitch": 71}, {"time": 9.9375, "pitch": 71}, {"time": 10.0, "pitch": 66}, {"time": 10.0625, "pitch": 66}, {"time": 10.125, "pitch": 66}, {"time": 10.1875, "pitch": 66}, {"time": 10.25, "pitch": 66}, {"time": 10.3125, "pitch": 66}, {"time": 10.375, "pitch": 66}, {"time": 10.4375, "pitch": 66}, {"time": 10.5, "pitch": 66}, {"time": 10.5625, "pitch": 66}, {"time": 10.625, "pitch": 66}, {"time": 10.6875, "pitch": 66}, {"time": 10.75, "pitch": 66}, {"time": 10.8125, "pitch": 66}, {"time": 10.875, "pitch": 66}, {"time": 10.9375, "pitch": 66}], "id": ["lsxp-LiangGuoJiao-ShiJieTing-1", "2"]}, {"lyrics": [{"time": 1.0, "lyric": "\u5c71"}, {"time": 1.5, "lyric": "\u9ad8"}, {"time": 4.0, "lyric": "\u8def"}, {"time": 5.0, "lyric": "\u8fdc"}, {"time": 8.0, "lyric": "\u5c11"}, {"time": 9.0, "lyric": "\u6765"}, {"time": 11.0, "lyric": "\u95ee"}, {"time": 12.0, "lyric": "\u5019\uff0c"}], "melody": [{"time": 1.0, "pitch": 68}, {"time": 1.0625, "pitch": 68}, {"time": 1.125, "pitch": 68}, {"time": 1.1875, "pitch": 68}, {"time": 1.25, "pitch": 66}, {"time": 1.3125, "pitch": 66}, {"time": 1.375, "pitch": 66}, {"time": 1.4375, "pitch": 66}, {"time": 1.5, "pitch": 68}, {"time": 1.5625, "pitch": 68}, {"time": 1.625, "pitch": 68}, {"time": 1.6875, "pitch": 68}, {"time": 1.75, "pitch": 68}, {"time": 1.8125, "pitch": 68}, {"time": 1.875, "pitch": 68}, {"time": 1.9375, "pitch": 68}, {"time": 2.0, "pitch": 68}, {"time": 2.0625, "pitch": 68}, {"time": 2.125, "pitch": 68}, {"time": 2.1875, "pitch": 68}, {"time": 2.25, "pitch": 68}, {"time": 2.3125, "pitch": 68}, {"time": 2.375, "pitch": 68}, {"time": 2.4375, "pitch": 68}, {"time": 2.5, "pitch": 66}, {"time": 2.5625, "pitch": 66}, {"time": 2.625, "pitch": 66}, {"time": 2.6875, "pitch": 66}, {"time": 2.75, "pitch": 66}, {"time": 2.8125, "pitch": 66}, {"time": 2.875, "pitch": 66}, {"time": 2.9375, "pitch": 66}, {"time": 3.0, "pitch": 61}, {"time": 3.0625, "pitch": 61}, {"time": 3.125, "pitch": 61}, {"time": 3.1875, "pitch": 61}, {"time": 3.25, "pitch": 64}, {"time": 3.3125, "pitch": 64}, {"time": 3.375, "pitch": 64}, {"time": 3.4375, "pitch": 64}, {"time": 3.5, "pitch": 61}, {"time": 3.5625, "pitch": 61}, {"time": 3.625, "pitch": 61}, {"time": 3.6875, "pitch": 61}, {"time": 3.75, "pitch": 61}, {"time": 3.8125, "pitch": 61}, {"time": 3.875, "pitch": 61}, {"time": 3.9375, "pitch": 61}, {"time": 4.0, "pitch": 64}, {"time": 4.0625, "pitch": 64}, {"time": 4.125, "pitch": 64}, {"time": 4.1875, "pitch": 64}, {"time": 4.25, "pitch": 64}, {"time": 4.3125, "pitch": 64}, {"time": 4.375, "pitch": 64}, {"time": 4.4375, "pitch": 64}, {"time": 4.5, "pitch": 61}, {"time": 4.5625, "pitch": 61}, {"time": 4.625, "pitch": 61}, {"time": 4.6875, "pitch": 61}, {"time": 4.75, "pitch": 68}, {"time": 4.8125, "pitch": 68}, {"time": 4.875, "pitch": 68}, {"time": 4.9375, "pitch": 68}, {"time": 5.0, "pitch": 66}, {"time": 5.0625, "pitch": 66}, {"time": 5.125, "pitch": 66}, {"time": 5.1875, "pitch": 66}, {"time": 5.25, "pitch": 66}, {"time": 5.3125, "pitch": 66}, {"time": 5.375, "pitch": 66}, {"time": 5.4375, "pitch": 66}, {"time": 5.5, "pitch": 61}, {"time": 5.5625, "pitch": 61}, {"time": 5.625, "pitch": 61}, {"time": 5.6875, "pitch": 61}, {"time": 5.75, "pitch": 64}, {"time": 5.8125, "pitch": 64}, {"time": 5.875, "pitch": 64}, {"time": 5.9375, "pitch": 64}, {"time": 6.0, "pitch": 59}, {"time": 6.0625, "pitch": 59}, {"time": 6.125, "pitch": 59}, {"time": 6.1875, "pitch": 59}, {"time": 6.25, "pitch": 0}, {"time": 6.3125, "pitch": 0}, {"time": 6.375, "pitch": 0}, {"time": 6.4375, "pitch": 0}, {"time": 6.5, "pitch": 0}, {"time": 6.5625, "pitch": 0}, {"time": 6.625, "pitch": 0}, {"time": 6.6875, "pitch": 0}, {"time": 6.75, "pitch": 0}, {"time": 6.8125, "pitch": 0}, {"time": 6.875, "pitch": 0}, {"time": 6.9375, "pitch": 0}, {"time": 7.0, "pitch": 0}, {"time": 7.0625, "pitch": 0}, {"time": 7.125, "pitch": 0}, {"time": 7.1875, "pitch": 0}, {"time": 7.25, "pitch": 0}, {"time": 7.3125, "pitch": 0}, {"time": 7.375, "pitch": 0}, {"time": 7.4375, "pitch": 0}, {"time": 7.5, "pitch": 0}, {"time": 7.5625, "pitch": 0}, {"time": 7.625, "pitch": 0}, {"time": 7.6875, "pitch": 0}, {"time": 7.75, "pitch": 0}, {"time": 7.8125, "pitch": 0}, {"time": 7.875, "pitch": 0}, {"time": 7.9375, "pitch": 0}, {"time": 8.0, "pitch": 63}, {"time": 8.0625, "pitch": 63}, {"time": 8.125, "pitch": 63}, {"time": 8.1875, "pitch": 63}, {"time": 8.25, "pitch": 63}, {"time": 8.3125, "pitch": 63}, {"time": 8.375, "pitch": 63}, {"time": 8.4375, "pitch": 63}, {"time": 8.5, "pitch": 63}, {"time": 8.5625, "pitch": 63}, {"time": 8.625, "pitch": 63}, {"time": 8.6875, "pitch": 63}, {"time": 8.75, "pitch": 66}, {"time": 8.8125, "pitch": 66}, {"time": 8.875, "pitch": 66}, {"time": 8.9375, "pitch": 66}, {"time": 9.0, "pitch": 61}, {"time": 9.0625, "pitch": 61}, {"time": 9.125, "pitch": 61}, {"time": 9.1875, "pitch": 61}, {"time": 9.25, "pitch": 63}, {"time": 9.3125, "pitch": 63}, {"time": 9.375, "pitch": 63}, {"time": 9.4375, "pitch": 63}, {"time": 9.5, "pitch": 66}, {"time": 9.5625, "pitch": 66}, {"time": 9.625, "pitch": 66}, {"time": 9.6875, "pitch": 66}, {"time": 9.75, "pitch": 66}, {"time": 9.8125, "pitch": 66}, {"time": 9.875, "pitch": 66}, {"time": 9.9375, "pitch": 66}, {"time": 10.0, "pitch": 66}, {"time": 10.0625, "pitch": 66}, {"time": 10.125, "pitch": 66}, {"time": 10.1875, "pitch": 66}, {"time": 10.25, "pitch": 66}, {"time": 10.3125, "pitch": 66}, {"time": 10.375, "pitch": 66}, {"time": 10.4375, "pitch": 66}, {"time": 10.5, "pitch": 0}, {"time": 10.5625, "pitch": 0}, {"time": 10.625, "pitch": 0}, {"time": 10.6875, "pitch": 0}, {"time": 10.75, "pitch": 0}, {"time": 10.8125, "pitch": 0}, {"time": 10.875, "pitch": 0}, {"time": 10.9375, "pitch": 0}, {"time": 11.0, "pitch": 56}, {"time": 11.0625, "pitch": 56}, {"time": 11.125, "pitch": 56}, {"time": 11.1875, "pitch": 56}, {"time": 11.25, "pitch": 59}, {"time": 11.3125, "pitch": 59}, {"time": 11.375, "pitch": 59}, {"time": 11.4375, "pitch": 59}, {"time": 11.5, "pitch": 56}, {"time": 11.5625, "pitch": 56}, {"time": 11.625, "pitch": 56}, {"time": 11.6875, "pitch": 56}, {"time": 11.75, "pitch": 59}, {"time": 11.8125, "pitch": 59}, {"time": 11.875, "pitch": 59}, {"time": 11.9375, "pitch": 59}, {"time": 12.0, "pitch": 61}, {"time": 12.0625, "pitch": 61}, {"time": 12.125, "pitch": 61}, {"time": 12.1875, "pitch": 61}, {"time": 12.25, "pitch": 61}, {"time": 12.3125, "pitch": 61}, {"time": 12.375, "pitch": 61}, {"time": 12.4375, "pitch": 61}, {"time": 12.5, "pitch": 61}, {"time": 12.5625, "pitch": 61}, {"time": 12.625, "pitch": 61}, {"time": 12.6875, "pitch": 61}, {"time": 12.75, "pitch": 63}, {"time": 12.8125, "pitch": 63}, {"time": 12.875, "pitch": 63}, {"time": 12.9375, "pitch": 63}, {"time": 13.0, "pitch": 66}, {"time": 13.0625, "pitch": 66}, {"time": 13.125, "pitch": 66}, {"time": 13.1875, "pitch": 66}, {"time": 13.25, "pitch": 66}, {"time": 13.3125, "pitch": 66}, {"time": 13.375, "pitch": 66}, {"time": 13.4375, "pitch": 66}, {"time": 13.5, "pitch": 66}, {"time": 13.5625, "pitch": 66}, {"time": 13.625, "pitch": 66}, {"time": 13.6875, "pitch": 66}, {"time": 13.75, "pitch": 66}, {"time": 13.8125, "pitch": 66}, {"time": 13.875, "pitch": 66}, {"time": 13.9375, "pitch": 66}, {"time": 14.0, "pitch": 64}, {"time": 14.0625, "pitch": 64}, {"time": 14.125, "pitch": 64}, {"time": 14.1875, "pitch": 64}, {"time": 14.25, "pitch": 64}, {"time": 14.3125, "pitch": 64}, {"time": 14.375, "pitch": 64}, {"time": 14.4375, "pitch": 64}, {"time": 14.5, "pitch": 64}, {"time": 14.5625, "pitch": 64}, {"time": 14.625, "pitch": 64}, {"time": 14.6875, "pitch": 64}, {"time": 14.75, "pitch": 66}, {"time": 14.8125, "pitch": 66}, {"time": 14.875, "pitch": 66}, {"time": 14.9375, "pitch": 66}, {"time": 15.0, "pitch": 63}, {"time": 15.0625, "pitch": 63}, {"time": 15.125, "pitch": 63}, {"time": 15.1875, "pitch": 63}, {"time": 15.25, "pitch": 66}, {"time": 15.3125, "pitch": 66}, {"time": 15.375, "pitch": 66}, {"time": 15.4375, "pitch": 66}, {"time": 15.5, "pitch": 63}, {"time": 15.5625, "pitch": 63}, {"time": 15.625, "pitch": 63}, {"time": 15.6875, "pitch": 63}, {"time": 15.75, "pitch": 59}, {"time": 15.8125, "pitch": 59}, {"time": 15.875, "pitch": 59}, {"time": 15.9375, "pitch": 59}, {"time": 16.0, "pitch": 61}, {"time": 16.0625, "pitch": 61}, {"time": 16.125, "pitch": 61}, {"time": 16.1875, "pitch": 61}, {"time": 16.25, "pitch": 61}, {"time": 16.3125, "pitch": 61}, {"time": 16.375, "pitch": 61}, {"time": 16.4375, "pitch": 61}, {"time": 16.5, "pitch": 61}, {"time": 16.5625, "pitch": 61}, {"time": 16.625, "pitch": 61}, {"time": 16.6875, "pitch": 61}, {"time": 16.75, "pitch": 61}, {"time": 16.8125, "pitch": 61}, {"time": 16.875, "pitch": 61}, {"time": 16.9375, "pitch": 61}], "id": ["lsxp-ZiCongQian-ZhuLianZhai", "0"]}], "legend": {"pitches": [{"name": "3", "midi": 56}, {"name": "5", "midi": 59}, {"name": "6", "midi": 61}, {"name": "7", "midi": 63}, {"name": "1", "midi": 64}, {"name": "2", "midi": 66}, {"name": "3", "midi": 68}, {"name": "4", "midi": 69}, {"name": "5", "midi": 71}, {"name": "6", "midi": 73}], "measures": [{"time": 0, "value": 1}, {"time": 2, "value": 2}, {"time": 4, "value": 3}, {"time": 6, "value": 4}, {"time": 8, "value": 5}, {"time": 10, "value": 6}, {"time": 12, "value": 7}, {"time": 14, "value": 8}, {"time": 16, "value": 9}], "titles": [{"title": "\u201c\u4e00\u4e8b\u65e0\u6210\u4e24\u9b13\u6591\u201d\u2014\u2014\u300a\u9c7c\u85cf\u5251\u300b\uff08\u4f0d\u5b50\u80e5\uff09", "id": "lsxp-YiShiWu-YuCangJian"}, {"title": "\u201c\u6df1\u5bab\u65e0\u5904\u4e0d\u98de\u82b1\u201d\u2014\u2014\u300a\u9f99\u51e4\u5448\u7965\u300b\uff08\u5218\u5907\uff09", "id": "lsxp-ShenGongWu-LongFengChengXiang"}, {"title": "\u201c\u6068\u5e73\u738b\u65e0\u9053\u4e71\u695a\u5bab\u201d\u2014\u2014\u300a\u6587\u662d\u5173\u300b\uff08\u4f0d\u5458\uff09", "id": "lsxp-HenPingWang-WenZhaoGuan"}, {"title": "\u201c\u4e24\u56fd\u4ea4\u950b\u9f99\u864e\u6597\u201d\u2014\u2014\u300a\u5931\u8857\u4ead\u300b\uff08\u8bf8\u845b\u4eae\uff09", "id": "lsxp-LiangGuoJiao-ShiJieTing-2"}, {"title": "\u201c\u4e24\u56fd\u4ea4\u950b\u9f99\u864e\u6597\u201d\u2014\u2014\u300a\u5931\u8857\u4ead\u300b\uff08\u8bf8\u845b\u4eae\uff09", "id": "lsxp-LiangGuoJiao-ShiJieTing-1"}, {"title": "\u201c\u81ea\u4ece\u5343\u5c81\u79bb\u6f6e\u540e\u201d\u2014\u2014\u300a\u73e0\u5e18\u5be8\u300b\uff08\u7a0b\u656c\u601d\uff09", "id": "lsxp-ZiCongQian-ZhuLianZhai"}], "upbeats": [1, 3, 5, 7, 9, 11, 13, 15]}}